Workbook

Sheet Summary
A1: Summary — 318 applicants
A3: Grade applied | B3: Applicants | C3: Share
A4: PreKG - Express Interest Now | B4: =COUNTIF('Applicant Insights'!$C$6:$C$350,"PreKG - Express Interest Now") -> 36 | C4: =IFERROR(B4/318,0) -> 0.11320755
A5: PreKG | B5: =COUNTIF('Applicant Insights'!$C$6:$C$350,"PreKG") -> 1 | C5: =IFERROR(B5/318,0) -> 0.0031446541
A6: LKG | B6: =COUNTIF('Applicant Insights'!$C$6:$C$350,"LKG") -> 40 | C6: =IFERROR(B6/318,0) -> 0.12578616
A7: UKG | B7: =COUNTIF('Applicant Insights'!$C$6:$C$350,"UKG") -> 21 | C7: =IFERROR(B7/318,0) -> 0.066037736
A8: Grade 1 | B8: =COUNTIF('Applicant Insights'!$C$6:$C$350,"Grade 1") -> 43 | C8: =IFERROR(B8/318,0) -> 0.13522013
A9: Grade 2 | B9: =COUNTIF('Applicant Insights'!$C$6:$C$350,"Grade 2") -> 22 | C9: =IFERROR(B9/318,0) -> 0.06918239
A10: Grade 3 | B10: =COUNTIF('Applicant Insights'!$C$6:$C$350,"Grade 3") -> 22 | C10: =IFERROR(B10/318,0) -> 0.06918239
A11: Grade 4 | B11: =COUNTIF('Applicant Insights'!$C$6:$C$350,"Grade 4") -> 27 | C11: =IFERROR(B11/318,0) -> 0.08490566
A12: Grade 5 | B12: =COUNTIF('Applicant Insights'!$C$6:$C$350,"Grade 5") -> 29 | C12: =IFERROR(B12/318,0) -> 0.091194969
A13: Grade 6 | B13: =COUNTIF('Applicant Insights'!$C$6:$C$350,"Grade 6") -> 19 | C13: =IFERROR(B13/318,0) -> 0.059748428
A14: Grade 7 | B14: =COUNTIF('Applicant Insights'!$C$6:$C$350,"Grade 7") -> 15 | C14: =IFERROR(B14/318,0) -> 0.047169811
A15: Grade 8 | B15: =COUNTIF('Applicant Insights'!$C$6:$C$350,"Grade 8") -> 18 | C15: =IFERROR(B15/318,0) -> 0.056603774
A16: Grade 9 | B16: =COUNTIF('Applicant Insights'!$C$6:$C$350,"Grade 9") -> 2 | C16: =IFERROR(B16/318,0) -> 0.0062893082
A17: Grade 11 | B17: =COUNTIF('Applicant Insights'!$C$6:$C$350,"Grade 11") -> 23 | C17: =IFERROR(B17/318,0) -> 0.072327044
A19: Estimated family income | B19: Applicants | C19: Share
A20: Below ₹15 L | B20: =COUNTIF('Applicant Insights'!$I$6:$I$350,"Below ₹15 L") -> 17 | C20: =IFERROR(B20/318,0) -> 0.053459119
A21: ₹15–30 L | B21: =COUNTIF('Applicant Insights'!$I$6:$I$350,"₹15–30 L") -> 34 | C21: =IFERROR(B21/318,0) -> 0.10691824
A22: ₹30–50 L | B22: =COUNTIF('Applicant Insights'!$I$6:$I$350,"₹30–50 L") -> 87 | C22: =IFERROR(B22/318,0) -> 0.27358491
A23: ₹50–80 L | B23: =COUNTIF('Applicant Insights'!$I$6:$I$350,"₹50–80 L") -> 83 | C23: =IFERROR(B23/318,0) -> 0.26100629
A24: ₹80 L and above | B24: =COUNTIF('Applicant Insights'!$I$6:$I$350,"₹80 L and above") -> 38 | C24: =IFERROR(B24/318,0) -> 0.11949686
A25: Not determinable | B25: =COUNTIF('Applicant Insights'!$I$6:$I$350,"Not determinable") -> 59 | C25: =IFERROR(B25/318,0) -> 0.18553459
A27: Proximity grade | B27: Applicants | C27: Share
A28: A — Doorstep (≤5 km) | B28: =COUNTIF('Applicant Insights'!$Q$6:$Q$350,"A — Doorstep (≤5 km)") -> 99 | C28: =IFERROR(B28/318,0) -> 0.31132075
A29: B — Near (5–10 km) | B29: =COUNTIF('Applicant Insights'!$Q$6:$Q$350,"B — Near (5–10 km)") -> 84 | C29: =IFERROR(B29/318,0) -> 0.26415094
A30: C — Commutable (10–15 km) | B30: =COUNTIF('Applicant Insights'!$Q$6:$Q$350,"C — Commutable (10–15 km)") -> 34 | C30: =IFERROR(B30/318,0) -> 0.10691824
A31: D — Far (15–25 km) | B31: =COUNTIF('Applicant Insights'!$Q$6:$Q$350,"D — Far (15–25 km)") -> 3 | C31: =IFERROR(B31/318,0) -> 0.0094339623
A32: E — Outside catchment (>25 km) | B32: =COUNTIF('Applicant Insights'!$Q$6:$Q$350,"E — Outside catchment (>25 km)") -> 7 | C32: =IFERROR(B32/318,0) -> 0.022012579
A33: U — Not determinable | B33: =COUNTIF('Applicant Insights'!$Q$6:$Q$350,"U — Not determinable") -> 91 | C33: =IFERROR(B33/318,0) -> 0.28616352
A35: Transfer out of Chennai | B35: Applicants | C35: Share
A36: High | B36: =COUNTIF('Applicant Insights'!$L$6:$L$350,"High") -> 24 | C36: =IFERROR(B36/318,0) -> 0.075471698
A37: Medium | B37: =COUNTIF('Applicant Insights'!$L$6:$L$350,"Medium") -> 95 | C37: =IFERROR(B37/318,0) -> 0.29874214
A38: Low | B38: =COUNTIF('Applicant Insights'!$L$6:$L$350,"Low") -> 199 | C38: =IFERROR(B38/318,0) -> 0.62578616
A40: Transfer out of India | B40: Applicants | C40: Share
A41: High | B41: =COUNTIF('Applicant Insights'!$M$6:$M$350,"High") -> 15 | C41: =IFERROR(B41/318,0) -> 0.047169811
A42: Medium | B42: =COUNTIF('Applicant Insights'!$M$6:$M$350,"Medium") -> 88 | C42: =IFERROR(B42/318,0) -> 0.27672956
A43: Low | B43: =COUNTIF('Applicant Insights'!$M$6:$M$350,"Low") -> 215 | C43: =IFERROR(B43/318,0) -> 0.67610063
A45: Profession 1 (father) | B45: Parents | C45: Share
A46: Homemaker | B46: =COUNTIF('Applicant Insights'!$G$6:$G$350,"Homemaker") -> 0 | C46: =IFERROR(B46/318,0) -> 0
A47: Healthcare | B47: =COUNTIF('Applicant Insights'!$G$6:$G$350,"Healthcare") -> 7 | C47: =IFERROR(B47/318,0) -> 0.022012579
A48: Law | B48: =COUNTIF('Applicant Insights'!$G$6:$G$350,"Law") -> 0 | C48: =IFERROR(B48/318,0) -> 0
A49: Teaching and academia | B49: =COUNTIF('Applicant Insights'!$G$6:$G$350,"Teaching and academia") -> 0 | C49: =IFERROR(B49/318,0) -> 0
A50: Government and defence | B50: =COUNTIF('Applicant Insights'!$G$6:$G$350,"Government and defence") -> 4 | C50: =IFERROR(B50/318,0) -> 0.012578616
A51: Business owner | B51: =COUNTIF('Applicant Insights'!$G$6:$G$350,"Business owner") -> 38 | C51: =IFERROR(B51/318,0) -> 0.11949686
A52: IT and software | B52: =COUNTIF('Applicant Insights'!$G$6:$G$350,"IT and software") -> 137 | C52: =IFERROR(B52/318,0) -> 0.43081761
A53: Banking and finance | B53: =COUNTIF('Applicant Insights'!$G$6:$G$350,"Banking and finance") -> 6 | C53: =IFERROR(B53/318,0) -> 0.018867925
A54: Engineering (non-IT) | B54: =COUNTIF('Applicant Insights'!$G$6:$G$350,"Engineering (non-IT)") -> 19 | C54: =IFERROR(B54/318,0) -> 0.059748428
A55: Management and consulting | B55: =COUNTIF('Applicant Insights'!$G$6:$G$350,"Management and consulting") -> 30 | C55: =IFERROR(B55/318,0) -> 0.094339623
A56: Media, design and arts | B56: =COUNTIF('Applicant Insights'!$G$6:$G$350,"Media, design and arts") -> 6 | C56: =IFERROR(B56/318,0) -> 0.018867925
A57: Other | B57: =COUNTIF('Applicant Insights'!$G$6:$G$350,"Other") -> 12 | C57: =IFERROR(B57/318,0) -> 0.037735849
A58: Not stated | B58: =COUNTIF('Applicant Insights'!$G$6:$G$350,"Not stated") -> 59 | C58: =IFERROR(B58/318,0) -> 0.18553459
A60: Profession 2 (mother) | B60: Parents | C60: Share
A61: Homemaker | B61: =COUNTIF('Applicant Insights'!$H$6:$H$350,"Homemaker") -> 82 | C61: =IFERROR(B61/318,0) -> 0.25786164
A62: Healthcare | B62: =COUNTIF('Applicant Insights'!$H$6:$H$350,"Healthcare") -> 5 | C62: =IFERROR(B62/318,0) -> 0.01572327
A63: Law | B63: =COUNTIF('Applicant Insights'!$H$6:$H$350,"Law") -> 0 | C63: =IFERROR(B63/318,0) -> 0
A64: Teaching and academia | B64: =COUNTIF('Applicant Insights'!$H$6:$H$350,"Teaching and academia") -> 12 | C64: =IFERROR(B64/318,0) -> 0.037735849
A65: Government and defence | B65: =COUNTIF('Applicant Insights'!$H$6:$H$350,"Government and defence") -> 0 | C65: =IFERROR(B65/318,0) -> 0
A66: Business owner | B66: =COUNTIF('Applicant Insights'!$H$6:$H$350,"Business owner") -> 22 | C66: =IFERROR(B66/318,0) -> 0.06918239
A67: IT and software | B67: =COUNTIF('Applicant Insights'!$H$6:$H$350,"IT and software") -> 81 | C67: =IFERROR(B67/318,0) -> 0.25471698
A68: Banking and finance | B68: =COUNTIF('Applicant Insights'!$H$6:$H$350,"Banking and finance") -> 8 | C68: =IFERROR(B68/318,0) -> 0.025157233
A69: Engineering (non-IT) | B69: =COUNTIF('Applicant Insights'!$H$6:$H$350,"Engineering (non-IT)") -> 1 | C69: =IFERROR(B69/318,0) -> 0.0031446541
A70: Management and consulting | B70: =COUNTIF('Applicant Insights'!$H$6:$H$350,"Management and consulting") -> 27 | C70: =IFERROR(B70/318,0) -> 0.08490566
A71: Media, design and arts | B71: =COUNTIF('Applicant Insights'!$H$6:$H$350,"Media, design and arts") -> 5 | C71: =IFERROR(B71/318,0) -> 0.01572327
A72: Other | B72: =COUNTIF('Applicant Insights'!$H$6:$H$350,"Other") -> 16 | C72: =IFERROR(B72/318,0) -> 0.050314465
A73: Not stated | B73: =COUNTIF('Applicant Insights'!$H$6:$H$350,"Not stated") -> 59 | C73: =IFERROR(B73/318,0) -> 0.18553459
A75: Why HLC — all reasons mentioned | B75: Applicants | C75: Share
A76: Holistic, all-round development | B76: =COUNTIF('Applicant Insights'!$U$6:$U$350,"*Holistic, all-round development*") -> 75 | C76: =IFERROR(B76/318,0) -> 0.23584906
A77: Child-centric, individual attention | B77: =COUNTIF('Applicant Insights'!$U$6:$U$350,"*Child-centric, individual attention*") -> 43 | C77: =IFERROR(B77/318,0) -> 0.13522013
A78: Stress-free, joyful learning | B78: =COUNTIF('Applicant Insights'!$U$6:$U$350,"*Stress-free, joyful learning*") -> 47 | C78: =IFERROR(B78/318,0) -> 0.14779874
A79: Experiential, hands-on learning | B79: =COUNTIF('Applicant Insights'!$U$6:$U$350,"*Experiential, hands-on learning*") -> 90 | C79: =IFERROR(B79/318,0) -> 0.28301887
A80: Values, nurturing environment and inclusion | B80: =COUNTIF('Applicant Insights'!$U$6:$U$350,"*Values, nurturing environment and inclusion*") -> 104 | C80: =IFERROR(B80/318,0) -> 0.32704403
A81: Cambridge, international curriculum | B81: =COUNTIF('Applicant Insights'!$U$6:$U$350,"*Cambridge, international curriculum*") -> 42 | C81: =IFERROR(B81/318,0) -> 0.13207547
A82: Life skills, confidence, leadership | B82: =COUNTIF('Applicant Insights'!$U$6:$U$350,"*Life skills, confidence, leadership*") -> 82 | C82: =IFERROR(B82/318,0) -> 0.25786164
A83: Teachers and facilitators | B83: =COUNTIF('Applicant Insights'!$U$6:$U$350,"*Teachers and facilitators*") -> 12 | C83: =IFERROR(B83/318,0) -> 0.037735849
A84: Recommendation and reputation | B84: =COUNTIF('Applicant Insights'!$U$6:$U$350,"*Recommendation and reputation*") -> 25 | C84: =IFERROR(B84/318,0) -> 0.078616352
A85: Proximity and convenience | B85: =COUNTIF('Applicant Insights'!$U$6:$U$350,"*Proximity and convenience*") -> 11 | C85: =IFERROR(B85/318,0) -> 0.034591195
A86: Sibling or continuity | B86: =COUNTIF('Applicant Insights'!$U$6:$U$350,"*Sibling or continuity*") -> 7 | C86: =IFERROR(B86/318,0) -> 0.022012579
A87: Sports and physical activity | B87: =COUNTIF('Applicant Insights'!$U$6:$U$350,"*Sports and physical activity*") -> 17 | C87: =IFERROR(B87/318,0) -> 0.053459119
A88: Quality and standards of education | B88: =COUNTIF('Applicant Insights'!$U$6:$U$350,"*Quality and standards of education*") -> 13 | C88: =IFERROR(B88/318,0) -> 0.040880503
A89: Interest and passion-led learning | B89: =COUNTIF('Applicant Insights'!$U$6:$U$350,"*Interest and passion-led learning*") -> 60 | C89: =IFERROR(B89/318,0) -> 0.18867925
A90: Special needs support | B90: =COUNTIF('Applicant Insights'!$U$6:$U$350,"*Special needs support*") -> 1 | C90: =IFERROR(B90/318,0) -> 0.0031446541
A92: Applicants with an existing HLC family in the same community | B92: =COUNTIF('Applicant Insights'!$R$6:$R$350,"<>0")-COUNTBLANK('Applicant Insights'!$R$6:$R$350) -> 318

Sheet Applicant Insights
A1: HLC International — Applicant Insights, AY 2026–27 cycle
A2: Internal and confidential. Income, mobility and distance are estimates from proxies — see the Method tab. Contact details deliberately excluded.
A4: APPLICANT | E4: FAMILY PROFILE | I4: ESTIMATED INCOME | L4: MOBILITY | O4: PROXIMITY | T4: WHY HLC
A5: # | B5: Applicant | C5: Grade applied | D5: Application date | E5: Father — occupation · role · employer | F5: Mother — occupation · role · employer | G5: Profession 1 (father) | H5: Profession 2 (mother) | I5: Family income band | J5: Range (₹ lakh a year) | K5: Confidence | L5: Transfer out of Chennai | M5: Transfer out of India | N5: Relocation note | O5: Locality | P5: Est. distance (km) | Q5: Proximity grade | R5: HLC families in same community | S5: HLC students in same locality | T5: Primary reason | U5: All reasons | V5: In their words
A6: PreKG - Express Interest Now · 36 applicants
A7: 1 | B7: R.Daanya | C7: PreKG - Express Interest Now | D7: 2025-11-01 | E7: — | F7: — | G7: Not stated | H7: Not stated | I7: Not determinable | J7: — | K7: — | L7: Low | M7: Low | O7: Not clear | P7: — | Q7: U — Not determinable | R7: 0 | S7: 0 | T7: Not stated / general | U7: Not stated / general
A8: 2 | B8: Srishti S. | C8: PreKG - Express Interest Now | D8: 2025-11-01 | E8: — | F8: — | G8: Not stated | H8: Not stated | I8: Not determinable | J8: — | K8: — | L8: Low | M8: Low | O8: Not clear | P8: — | Q8: U — Not determinable | R8: 0 | S8: 0 | T8: Not stated / general | U8: Not stated / general
A9: 3 | B9: KANISHA | C9: PreKG - Express Interest Now | D9: 2025-11-01 | E9: — | F9: — | G9: Not stated | H9: Not stated | I9: Not determinable | J9: — | K9: — | L9: Low | M9: Low | O9: Not clear | P9: — | Q9: U — Not determinable | R9: 0 | S9: 0 | T9: Not stated / general | U9: Not stated / general
A10: 4 | B10: Yuktha Kishore | C10: PreKG - Express Interest Now | D10: 2025-11-01 | E10: — | F10: — | G10: Not stated | H10: Not stated | I10: Not determinable | J10: — | K10: — | L10: Low | M10: Low | O10: Not clear | P10: — | Q10: U — Not determinable | R10: 0 | S10: 0 | T10: Not stated / general | U10: Not stated / general
A11: 5 | B11: Nila.R | C11: PreKG - Express Interest Now | D11: 2025-11-01 | E11: — | F11: — | G11: Not stated | H11: Not stated | I11: Not determinable | J11: — | K11: — | L11: Low | M11: Low | O11: Not clear | P11: — | Q11: U — Not determinable | R11: 0 | S11: 0 | T11: Not stated / general | U11: Not stated / general
A12: 6 | B12: R.Nila | C12: PreKG - Express Interest Now | D12: 2025-11-01 | E12: — | F12: — | G12: Not stated | H12: Not stated | I12: Not determinable | J12: — | K12: — | L12: Low | M12: Low | O12: Not clear | P12: — | Q12: U — Not determinable | R12: 0 | S12: 0 | T12: Not stated / general | U12: Not stated / general
A13: 7 | B13: Dhriti Ram | C13: PreKG - Express Interest Now | D13: 2025-11-01 | E13: — | F13: — | G13: Not stated | H13: Not stated | I13: Not determinable | J13: — | K13: — | L13: Low | M13: Low | O13: Not clear | P13: — | Q13: U — Not determinable | R13: 0 | S13: 0 | T13: Not stated / general | U13: Not stated / general
A14: 8 | B14: Meenakshi Vijayalakshmi Kartik | C14: PreKG - Express Interest Now | D14: 2025-11-02 | E14: — | F14: — | G14: Not stated | H14: Not stated | I14: Not determinable | J14: — | K14: — | L14: Low | M14: Low | O14: Not clear | P14: — | Q14: U — Not determinable | R14: 0 | S14: 0 | T14: Not stated / general | U14: Not stated / general
A15: 9 | B15: Rhythm | C15: PreKG - Express Interest Now | D15: 2025-11-03 | E15: — | F15: — | G15: Not stated | H15: Not stated | I15: Not determinable | J15: — | K15: — | L15: Low | M15: Low | O15: Not clear | P15: — | Q15: U — Not determinable | R15: 0 | S15: 0 | T15: Not stated / general | U15: Not stated / general
A16: 10 | B16: Iniya Madhavan | C16: PreKG - Express Interest Now | D16: 2025-11-03 | E16: — | F16: — | G16: Not stated | H16: Not stated | I16: Not determinable | J16: — | K16: — | L16: Low | M16: Low | O16: Not clear | P16: — | Q16: U — Not determinable | R16: 0 | S16: 0 | T16: Not stated / general | U16: Not stated / general
A17: 11 | B17: N.Nia Nithwin | C17: PreKG - Express Interest Now | D17: 2025-11-03 | E17: — | F17: — | G17: Not stated | H17: Not stated | I17: Not determinable | J17: — | K17: — | L17: Low | M17: Low | O17: Not clear | P17: — | Q17: U — Not determinable | R17: 0 | S17: 0 | T17: Not stated / general | U17: Not stated / general
A18: 12 | B18: Arshad Siddique | C18: PreKG - Express Interest Now | D18: 2025-11-03 | E18: Software engineer · Associate Vice President · Softeon | F18: Software engineer · Technical lead · Tata consultancy services | G18: IT and software | H18: IT and software | I18: ₹80 L and above | J18: 68–135 | K18: Medium | L18: Medium | M18: Medium | O18: Thalambur | P18: 3 | Q18: A — Doorstep (≤5 km) | R18: 3 (Casagrande Pavilion) | S18: 37 | T18: Child-centric, individual attention | U18: Child-centric, individual attention, Stress-free, joyful learning, Experiential, hands-on learning, Values, nurturing environment and inclusion, Life skills, confidence, leadership, Quality and standards of education, Interest and passion-led learning | V18: I’m choosing HLC because it offers a child-centred, experiential approach to education. I appreciate that HLC focuses on developing life skills, critical thinki…
A19: 13 | B19: Shawn Marcello S | C19: PreKG - Express Interest Now | D19: 2025-11-04 | E19: — | F19: — | G19: Not stated | H19: Not stated | I19: Not determinable | J19: — | K19: — | L19: Low | M19: Low | O19: Not clear | P19: — | Q19: U — Not determinable | R19: 0 | S19: 0 | T19: Not stated / general | U19: Not stated / general
A20: 14 | B20: Dheekshitha Dhivakar | C20: PreKG - Express Interest Now | D20: 2025-11-05 | E20: — | F20: — | G20: Not stated | H20: Not stated | I20: Not determinable | J20: — | K20: — | L20: Low | M20: Low | O20: Not clear | P20: — | Q20: U — Not determinable | R20: 0 | S20: 0 | T20: Not stated / general | U20: Not stated / general
A21: 15 | B21: Gayan Dev S | C21: PreKG - Express Interest Now | D21: 2025-11-05 | E21: — | F21: — | G21: Not stated | H21: Not stated | I21: Not determinable | J21: — | K21: — | L21: Low | M21: Low | O21: Not clear | P21: — | Q21: U — Not determinable | R21: 0 | S21: 0 | T21: Not stated / general | U21: Not stated / general
A22: 16 | B22: KRISHAV | C22: PreKG - Express Interest Now | D22: 2025-11-07 | E22: — | F22: — | G22: Not stated | H22: Not stated | I22: Not determinable | J22: — | K22: — | L22: Low | M22: Low | O22: Not clear | P22: — | Q22: U — Not determinable | R22: 0 | S22: 0 | T22: Not stated / general | U22: Not stated / general
A23: 17 | B23: Adhira A | C23: PreKG - Express Interest Now | D23: 2025-11-08 | E23: — | F23: — | G23: Not stated | H23: Not stated | I23: Not determinable | J23: — | K23: — | L23: Low | M23: Low | O23: Not clear | P23: — | Q23: U — Not determinable | R23: 0 | S23: 0 | T23: Not stated / general | U23: Not stated / general
A24: 18 | B24: Vanshika | C24: PreKG - Express Interest Now | D24: 2025-11-09 | E24: — | F24: — | G24: Not stated | H24: Not stated | I24: Not determinable | J24: — | K24: — | L24: Low | M24: Low | O24: Not clear | P24: — | Q24: U — Not determinable | R24: 0 | S24: 0 | T24: Not stated / general | U24: Not stated / general
A25: 19 | B25: karthikeyan B | C25: PreKG - Express Interest Now | D25: 2025-11-11 | E25: — | F25: — | G25: Not stated | H25: Not stated | I25: Not determinable | J25: — | K25: — | L25: Low | M25: Low | O25: Not clear | P25: — | Q25: U — Not determinable | R25: 0 | S25: 0 | T25: Not stated / general | U25: Not stated / general
A26: 20 | B26: K.S Aruvi | C26: PreKG - Express Interest Now | D26: 2025-11-11 | E26: — | F26: — | G26: Not stated | H26: Not stated | I26: Not determinable | J26: — | K26: — | L26: Low | M26: Low | O26: Not clear | P26: — | Q26: U — Not determinable | R26: 0 | S26: 0 | T26: Not stated / general | U26: Not stated / general
A27: 21 | B27: A.k.Mahat krishna | C27: PreKG - Express Interest Now | D27: 2025-11-13 | E27: Radiologist · Proprietor · Dr.anand's scan | F27: Home maker · Home maker · Home maker | G27: Healthcare | H27: Homemaker | I27: ₹30–50 L | J27: 20–50 | K27: Medium | L27: Low | M27: Low | O27: Karanai | P27: 1 | Q27: A — Doorstep (≤5 km) | R27: 14 (Jones Cassia) | S27: 13 | T27: Stress-free, joyful learning | U27: Stress-free, joyful learning | V27: Very happy with our first kid progress
A28: 22 | B28: Tharika V | C28: PreKG - Express Interest Now | D28: 2025-11-20 | E28: Supply Chain · Manager · Ford | F28: Career break · Previously worked as an HR operations lead · Not working currently | G28: Management and consulting | H28: Management and consulting | I28: ₹50–80 L | J28: 39–78 | K28: Medium | L28: Medium | M28: Medium | O28: Ottiyambakkam | P28: 11 | Q28: C — Commutable (10–15 km) | R28: 0 | S28: 9 | T28: Child-centric, individual attention | U28: Child-centric, individual attention, Stress-free, joyful learning, Experiential, hands-on learning, Values, nurturing environment and inclusion, Life skills, confidence, leadership, Interest and passion-led learning | V28: We are seeking HLC for our child because we believe in an environment that encourages curiosity, independence, and joyful learning. HLC’s philosophy of nurturin…
A29: 23 | B29: Aadhiran Jayaprathap | C29: PreKG - Express Interest Now | D29: 2025-11-25 | E29: — | F29: — | G29: Not stated | H29: Not stated | I29: Not determinable | J29: — | K29: — | L29: Low | M29: Low | O29: Not clear | P29: — | Q29: U — Not determinable | R29: 0 | S29: 0 | T29: Not stated / general | U29: Not stated / general
A30: 24 | B30: LASYA SHREE A | C30: PreKG - Express Interest Now | D30: 2025-11-25 | E30: — | F30: — | G30: Not stated | H30: Not stated | I30: Not determinable | J30: — | K30: — | L30: Low | M30: Low | O30: Not clear | P30: — | Q30: U — Not determinable | R30: 0 | S30: 0 | T30: Not stated / general | U30: Not stated / general
A31: 25 | B31: Adelina carlin | C31: PreKG - Express Interest Now | D31: 2025-11-25 | E31: — | F31: — | G31: Not stated | H31: Not stated | I31: Not determinable | J31: — | K31: — | L31: Low | M31: Low | O31: Not clear | P31: — | Q31: U — Not determinable | R31: 0 | S31: 0 | T31: Not stated / general | U31: Not stated / general
A32: 26 | B32: Hridhaan Shyam | C32: PreKG - Express Interest Now | D32: 2025-11-26 | E32: — | F32: — | G32: Not stated | H32: Not stated | I32: Not determinable | J32: — | K32: — | L32: Low | M32: Low | O32: Not clear | P32: — | Q32: U — Not determinable | R32: 0 | S32: 0 | T32: Not stated / general | U32: Not stated / general
A33: 27 | B33: Iyaan | C33: PreKG - Express Interest Now | D33: 2025-12-01 | E33: — | F33: — | G33: Not stated | H33: Not stated | I33: Not determinable | J33: — | K33: — | L33: Low | M33: Low | O33: Not clear | P33: — | Q33: U — Not determinable | R33: 0 | S33: 0 | T33: Not stated / general | U33: Not stated / general
A34: 28 | B34: Ayra Parry | C34: PreKG - Express Interest Now | D34: 2025-12-12 | E34: — | F34: — | G34: Not stated | H34: Not stated | I34: Not determinable | J34: — | K34: — | L34: Low | M34: Low | O34: Not clear | P34: — | Q34: U — Not determinable | R34: 0 | S34: 0 | T34: Not stated / general | U34: Not stated / general
A35: 29 | B35: Aadhiran.P.S | C35: PreKG - Express Interest Now | D35: 2025-12-18 | E35: — | F35: — | G35: Not stated | H35: Not stated | I35: Not determinable | J35: — | K35: — | L35: Low | M35: Low | O35: Not clear | P35: — | Q35: U — Not determinable | R35: 0 | S35: 0 | T35: Not stated / general | U35: Not stated / general
A36: 30 | B36: SAANVI V | C36: PreKG - Express Interest Now | D36: 2025-12-30 | E36: — | F36: — | G36: Not stated | H36: Not stated | I36: Not determinable | J36: — | K36: — | L36: Low | M36: Low | O36: Not clear | P36: — | Q36: U — Not determinable | R36: 0 | S36: 0 | T36: Not stated / general | U36: Not stated / general
A37: 31 | B37: Aaradhya Vignesh | C37: PreKG - Express Interest Now | D37: 2025-12-30 | E37: — | F37: — | G37: Not stated | H37: Not stated | I37: Not determinable | J37: — | K37: — | L37: Low | M37: Low | O37: Not clear | P37: — | Q37: U — Not determinable | R37: 0 | S37: 0 | T37: Not stated / general | U37: Not stated / general
A38: 32 | B38: Reehaa S Palani | C38: PreKG - Express Interest Now | D38: 2026-01-04 | E38: — | F38: — | G38: Not stated | H38: Not stated | I38: Not determinable | J38: — | K38: — | L38: Low | M38: Low | O38: Not clear | P38: — | Q38: U — Not determinable | R38: 0 | S38: 0 | T38: Not stated / general | U38: Not stated / general
A39: 33 | B39: Hamsika V | C39: PreKG - Express Interest Now | D39: 2026-01-09 | E39: — | F39: — | G39: Not stated | H39: Not stated | I39: Not determinable | J39: — | K39: — | L39: Low | M39: Low | O39: Not clear | P39: — | Q39: U — Not determinable | R39: 0 | S39: 0 | T39: Not stated / general | U39: Not stated / general
A40: 34 | B40: Thara | C40: PreKG - Express Interest Now | D40: 2026-01-10 | E40: — | F40: — | G40: Not stated | H40: Not stated | I40: Not determinable | J40: — | K40: — | L40: Low | M40: Low | O40: Not clear | P40: — | Q40: U — Not determinable | R40: 0 | S40: 0 | T40: Not stated / general | U40: Not stated / general
... A42: 36 | B42: Vedh Nandan | C42: PreKG - Express Interest Now | D42: 2026-01-13 | E42: — | F42: — | G42: Not stated | H42: Not stated | I42: Not determinable | J42: — | K42: — | L42: Low | M42: Low | O42: Not clear | P42: — | Q42: U — Not determinable | R42: 0 | S42: 0 | T42: Not stated / general | U42: Not stated / general
A44: PreKG · 1 applicant
A45: 37 | B45: KIYAN KIRAN | C45: PreKG | D45: 2026-01-13 | E45: INFORMATION TECHNOLOGY · TECHNICAL ACCOUNT MANAGER · LIKEWIZE | F45: INFORMATION TECHNOLOGY · MANAGER SOLUTION ARCHITECT · DXC TECHNOLOGY | G45: IT and software | H45: IT and software | I45: ₹50–80 L | J45: 48–90 | K45: Medium | L45: Low | M45: Low | O45: Perumbakkam | P45: 9 | Q45: B — Near (5–10 km) | R45: 3 (Embassy) | S45: 51 | T45: Holistic, all-round development | U45: Holistic, all-round development, Values, nurturing environment and inclusion, Recommendation and reputation | V45: After reviewing the website, we feel the outcomes we seek for our child align closely with what HLC offers. We are hopeful that an education at HLC will go beyo…
A47: LKG · 40 applicants
A48: 38 | B48: Harvik S | C48: LKG | D48: 2025-11-01 | E48: IT · project Manager · standard Chartered Bank | F48: IT · test Lead · TCS | G48: IT and software | H48: IT and software | I48: ₹50–80 L | J48: 39–78 | K48: Medium | L48: High | M48: Medium | O48: Karanai | P48: 1 | Q48: A — Doorstep (≤5 km) | R48: 2 (Casagrand Divinity) | S48: 13 | T48: Holistic, all-round development | U48: Holistic, all-round development | V48: Because am looking for a Holistic approach to education
A49: 39 | B49: Rana Sathya Goutham | C49: LKG | D49: 2025-11-01 | E49: Software Engineer · Specialist, Software Technology · KLA | F49: Architect · Architect · Self-Employed (Niche Studio) | G49: IT and software | H49: Media, design and arts | I49: ₹50–80 L | J49: 48–90 | K49: Medium | L49: Low | M49: Low | O49: Sholinganallur | P49: 6 | Q49: B — Near (5–10 km) | R49: 4 (Ceebros Belvedere) | S49: 22 | T49: Child-centric, individual attention | U49: Child-centric, individual attention, Stress-free, joyful learning, Experiential, hands-on learning, Values, nurturing environment and inclusion, Life skills, confidence, leadership, Interest and passion-led learning | V49: We are seeking HLC as the learning centre for our child because its philosophy deeply resonates with our own. We have visited the school and met Naveen and Raaj…
A50: 40 | B50: Mihika Kalaivanan | C50: LKG | D50: 2025-11-01 | E50: Salaried · Associate Consultant · TCS | F50: Salaried · Product Manager · Mocha Technologies | G50: Management and consulting | H50: IT and software | I50: ₹50–80 L | J50: 36–70 | K50: Medium | L50: Medium | M50: Medium | O50: Perumbakkam | P50: 9 | Q50: B — Near (5–10 km) | R50: 0 | S50: 51 | T50: Child-centric, individual attention | U50: Child-centric, individual attention, Stress-free, joyful learning, Experiential, hands-on learning, Values, nurturing environment and inclusion, Life skills, confidence, leadership, Teachers and facilitators | V50: HLC's focus on nurturing child's inherent curiosity is what stood out for us. We believe education should be highly personal, if given a chance each child has t…
A51: 41 | B51: Nyrah P | C51: LKG | D51: 2025-11-01 | E51: Employee · People Analyst · KLA Tencor | F51: Business · Founder · Nyrah Luxe | G51: Management and consulting | H51: Business owner | I51: ₹30–50 L | J51: 23–70 | K51: Medium | L51: Low | M51: Low | O51: Thalambur | P51: 3 | Q51: A — Doorstep (≤5 km) | R51: 0 | S51: 37 | T51: Sports and physical activity | U51: Sports and physical activity, Quality and standards of education | V51: To give best education and sports to my daughter
A52: 42 | B52: NILAN S | C52: LKG | D52: 2025-11-02 | E52: Private employement · Deputy manager · Ford Motor private limited | F52: Software Engineer · Senior test lead · Wipro limited | G52: Management and consulting | H52: IT and software | I52: ₹50–80 L | J52: 39–78 | K52: Medium | L52: Medium | M52: Medium | O52: Perumbakkam | P52: 9 | Q52: B — Near (5–10 km) | R52: 2 (Radiance) | S52: 51 | T52: Experiential, hands-on learning | U52: Experiential, hands-on learning, Values, nurturing environment and inclusion | V52: HLC’s focus on hands-on learning, values, and a nurturing atmosphere makes it the ideal school for our child.
A53: 43 | B53: Jai Dvithi | C53: LKG | D53: 2025-11-03 | E53: IT Professional · Lead Engineer · Renault Nissan | F53: IT Professional · Team Lead · Infosys limited | G53: IT and software | H53: IT and software | I53: ₹50–80 L | J53: 39–78 | K53: Medium | L53: Medium | M53: Medium | O53: Vengadamangalam | P53: 12 | Q53: C — Commutable (10–15 km) | R53: 0 | S53: 0 | T53: Recommendation and reputation | U53: Recommendation and reputation | V53: Strong academic reputation
A54: 44 | B54: Isabella Tom | C54: LKG | D54: 2025-11-03 | E54: Software Engineer · Developer · Cognizant | F54: Not working · Nil · Nil | G54: IT and software | H54: Homemaker | I54: Below ₹15 L | J54: 8–20 | K54: Medium | L54: Medium | M54: Low | O54: Karanai | P54: 1 | Q54: A — Doorstep (≤5 km) | R54: 0 | S54: 13 | T54: Child-centric, individual attention | U54: Child-centric, individual attention, Stress-free, joyful learning, Teachers and facilitators | V54: We are seeking HLC because its child‑centred, play‑based early years programme and experienced staff best support our daughter’s social‑emotional development an…
A55: 45 | B55: Dakshan VS | C55: LKG | D55: 2025-11-03 | E55: Software Engineer · Senior software Engineer · Mondu | F55: Homemaker · NA · NA | G55: IT and software | H55: Homemaker | I55: Below ₹15 L | J55: 8–20 | K55: Medium | L55: Low | M55: Low | O55: Pallikaranai | P55: 12 | Q55: C — Commutable (10–15 km) | R55: 0 | S55: 6 | T55: Stress-free, joyful learning | U55: Stress-free, joyful learning, Experiential, hands-on learning, Values, nurturing environment and inclusion, Life skills, confidence, leadership | V55: We’re seeking HLC for our child because we love how the school focuses on nurturing curiosity, confidence, and creativity from an early age which aligns perfect…
A56: 46 | B56: Brayden Matthew S | C56: LKG | D56: 2025-11-04 | E56: IT Professional · Senior Software Engineer · Optum | F56: Home Maker · Home Maker · Home Maker | G56: IT and software | H56: Homemaker | I56: Below ₹15 L | J56: 8–20 | K56: Medium | L56: Low | M56: Low | O56: Siruseri | P56: 6 | Q56: B — Near (5–10 km) | R56: 0 | S56: 14 | T56: Life skills, confidence, leadership | U56: Life skills, confidence, leadership, Quality and standards of education | V56: We are seeking HLC because we recognize its strong focus on academic excellence and structured learning. We believe this rigorous foundation is essential to hel…
A57: 47 | B57: SASTIKA | C57: LKG | D57: 2025-11-04 | E57: IT · NPO ENGINEER · NOKIA | F57: IT · TECHNICAL SPECIALIST · HEXAWARE | G57: IT and software | H57: IT and software | I57: ₹30–50 L | J57: 26–55 | K57: Medium | L57: Medium | M57: Low | O57: Thalambur | P57: 3 | Q57: A — Doorstep (≤5 km) | R57: 0 | S57: 37 | T57: Interest and passion-led learning | U57: Interest and passion-led learning | V57: Combining the proper education with a child's interest and passion
A58: 48 | B58: Vivaan | C58: LKG | D58: 2025-11-05 | E58: Software Engineer · Solution Delivery Advisor · Deloitte | F58: Housewife · NA · NA | G58: IT and software | H58: Homemaker | I58: ₹15–30 L | J58: 9–25 | K58: Medium | L58: Medium | M58: Medium | O58: Perungudi | P58: 12 | Q58: C — Commutable (10–15 km) | R58: 3 (Planning) | S58: 3 | T58: Life skills, confidence, leadership | U58: Life skills, confidence, leadership, Sports and physical activity | V58: We believe HLC provides the right environment for our child to learn meaningfully, grow with confidence, and develop into a capable and grounded individual.
A59: 49 | B59: S SANVIKA | C59: LKG | D59: 2025-11-05 | E59: Professional · Marketing Manager · Fourrts India Laboratories | F59: professional · Marketing Manager · Fourrts India | G59: Management and consulting | H59: Management and consulting | I59: ₹50–80 L | J59: 36–70 | K59: Medium | L59: Low | M59: Low | O59: Thalambur | P59: 3 | Q59: A — Doorstep (≤5 km) | R59: 0 | S59: 37 | T59: Stress-free, joyful learning | U59: Stress-free, joyful learning, Experiential, hands-on learning, Values, nurturing environment and inclusion | V59: We’re looking for a school that values curiosity and individuality as much as academic performance. HLC’s approach to hands-on learning and its emphasis on empa…
... A61: 51 | B61: Vamshika | C61: LKG | D61: 2025-11-10 | E61: Software Engineer · Technology Specialist · IBM | F61: Software Engineer · Senior Associate · PWC | G61: IT and software | H61: IT and software | I61: ₹30–50 L | J61: 30–68 | K61: Medium | L61: Medium | M61: Medium | O61: Siruseri | P61: 6 | Q61: B — Near (5–10 km) | R61: 0 | S61: 14 | T61: Holistic, all-round development | U61: Holistic, all-round development, Stress-free, joyful learning, Experiential, hands-on learning, Values, nurturing environment and inclusion | V61: We believe that HLC provides a joyful and nurturing environment where our child can learn, explore, and grow holistically.
A62: 52 | B62: A Manukarnika Reddy | C62: LKG | D62: 2025-11-10 | E62: Business · Owner · Transport | F62: Self employed · Director · Caballoconstructions | G62: Business owner | H62: Business owner | I62: ₹50–80 L | J62: 30–100 | K62: Medium | L62: Low | M62: Low | O62: Not clear | P62: — | Q62: U — Not determinable | R62: 0 | S62: 0 | T62: Experiential, hands-on learning | U62: Experiential, hands-on learning | V62: For creative learning experience to our child
A63: 53 | B63: S Arjun | C63: LKG | D63: 2025-11-10 | E63: Private Sector- IT · Director · Ninjacart | F63: Private Sector- IT · Technical Lead · Bahwan Cybertek | G63: IT and software | H63: IT and software | I63: ₹80 L and above | J63: 68–135 | K63: Medium | L63: Low | M63: Low | O63: Thoraipakkam | P63: 10 | Q63: B — Near (5–10 km) | R63: 0 | S63: 2 | T63: Holistic, all-round development | U63: Holistic, all-round development, Values, nurturing environment and inclusion, Life skills, confidence, leadership, Sibling or continuity, Quality and standards of education | V63: Our daughter is currently studying at HLC( Mahima - Grade3), and we have observed significant intellectual and emotional growth in her through the school’s holi…
A64: 54 | B64: Dharshik Azhagu Kumaran | C64: LKG | D64: 2025-11-11 | E64: HR manger · Senior manager · Hexaware technologies Ltd Chennai | F64: IT software engineer · Senior Data engineer · Tiger Analytics Chennai | G64: Management and consulting | H64: IT and software | I64: ₹50–80 L | J64: 38–75 | K64: Medium | L64: Medium | M64: Medium | O64: Thalambur | P64: 3 | Q64: A — Doorstep (≤5 km) | R64: 0 | S64: 37 | T64: Holistic, all-round development | U64: Holistic, all-round development, Experiential, hands-on learning, Values, nurturing environment and inclusion, Life skills, confidence, leadership, Recommendation and reputation, Interest and passion-led learning | V64: We chose HLC because of its reputation for holistic, experiential education and its focus on developing life skills, creativity, and emotional well-being along …
A65: 55 | B65: N Siddhanth Raju | C65: LKG | D65: 2025-11-12 | E65: Employee · IT consultant · Accenture | F65: Housewife · Housewife · Housewife | G65: IT and software | H65: Homemaker | I65: ₹15–30 L | J65: 18–35 | K65: Medium | L65: Medium | M65: Medium | O65: Semmancheri | P65: 4 | Q65: A — Doorstep (≤5 km) | R65: 8 (Dinesh Vihar) | S65: 10 | T65: Teachers and facilitators | U65: Teachers and facilitators, Recommendation and reputation | V65: At HLC each kid is given equal importance. We also admire the relationship between faculty and the student. They make the children feel safe and heard.
A66: 56 | B66: Tanya Narayanan | C66: LKG | D66: 2025-11-14 | E66: Business · Proprietor · Velavan Agency | F66: NA · NA · NA | G66: Business owner | H66: Other | I66: ₹30–50 L | J66: 21–65 | K66: Medium | L66: Low | M66: Low | O66: Kazhipattur | P66: 7 | Q66: B — Near (5–10 km) | R66: 1 (Ouranya Bay) | S66: 7 | T66: Stress-free, joyful learning | U66: Stress-free, joyful learning, Cambridge, international curriculum, Teachers and facilitators, Interest and passion-led learning | V66: In HLC, we feel the emphasis is on the child's interests and passions than the curriculum and also not like the conventional schools where academics pressure is…
A67: 57 | B67: Jahaan Sahoo | C67: LKG | D67: 2025-11-15 | E67: Service · Company Secretary · Yamaha Motor India | F67: Service · Process lead Finance · Capgemini India | G67: Other | H67: Banking and finance | I67: ₹30–50 L | J67: 24–50 | K67: Medium | L67: Medium | M67: Medium | O67: Sholinganallur | P67: 6 | Q67: B — Near (5–10 km) | R67: 0 | S67: 22 | T67: Not stated / general | U67: Not stated / general | V67: Yes
A68: 58 | B68: Aathiran Hariprasad | C68: LKG | D68: 2025-11-19 | E68: Information Technology · Software developer · Amazon | F68: House Wife · NA · House Wife | G68: IT and software | H68: Homemaker | I68: ₹15–30 L | J68: 9–25 | K68: Medium | L68: Medium | M68: Medium | O68: Sholinganallur | P68: 6 | Q68: B — Near (5–10 km) | R68: 1 (Front Model) | S68: 22 | T68: Child-centric, individual attention | U68: Child-centric, individual attention | V68: HLC is known for its child-centric approach and we love to be child to be part of this learning center
A69: 59 | B69: Dhruvan .G | C69: LKG | D69: 2025-11-21 | E69: — | F69: — | G69: Not stated | H69: Not stated | I69: Not determinable | J69: — | K69: — | L69: Low | M69: Low | O69: Not clear | P69: — | Q69: U — Not determinable | R69: 0 | S69: 0 | T69: Not stated / general | U69: Not stated / general
A70: 60 | B70: Vedh Jacob Gautham | C70: LKG | D70: 2025-11-26 | E70: IT engineer · Cyber security engineer · Persistent Systems | F70: IT · NA · Currently on sabbatical | G70: IT and software | H70: IT and software | I70: ₹15–30 L | J70: 16–38 | K70: Medium | L70: Low | M70: Low | O70: Perumbakkam | P70: 9 | Q70: B — Near (5–10 km) | R70: 1 (Oxygen Urban) | S70: 51 | T70: Holistic, all-round development | U70: Holistic, all-round development, Stress-free, joyful learning, Values, nurturing environment and inclusion | V70: Looking for a holistic environment that is gentle and value oriented without undue pressure
A71: 61 | B71: Sadhiv Sachin | C71: LKG | D71: 2025-12-01 | E71: IT professional · Tech Lead · TCS,Chennai | F71: Home maker · Nil · Nil | G71: IT and software | H71: Homemaker | I71: ₹15–30 L | J71: 18–35 | K71: Medium | L71: Medium | M71: Medium | O71: Siruseri | P71: 6 | Q71: B — Near (5–10 km) | R71: 3 (Jasmine) | S71: 14 | T71: Experiential, hands-on learning | U71: Experiential, hands-on learning, Values, nurturing environment and inclusion, Life skills, confidence, leadership | V71: One that nurtures curiosity , confidence and independent thinking
A72: 62 | B72: J.S.Mithra | C72: LKG | D72: 2025-12-01 | E72: IT · Data analyst · Optum health and technology private limited | F72: Home maker · Home maker · Na | G72: IT and software | H72: Homemaker | I72: Below ₹15 L | J72: 8–20 | K72: Medium | L72: Low | M72: Low | O72: Thalambur | P72: 3 | Q72: A — Doorstep (≤5 km) | R72: 0 | S72: 37 | T72: Holistic, all-round development | U72: Holistic, all-round development, Stress-free, joyful learning, Experiential, hands-on learning, Values, nurturing environment and inclusion | V72: We chose HLC because it offers a holistic learning environment that nurtures curiosity, individuality, and joy in learning. Its balanced approach supports both …
A73: 63 | B73: Dheera Deepak | C73: LKG | D73: 2025-12-03 | E73: Project sales - cement and mining · Business development manager · Timken | F73: IT · Functional architect · BlueYonder | G73: Business owner | H73: IT and software | I73: ₹50–80 L | J73: 45–105 | K73: Medium | L73: Low | M73: Low | O73: Thalambur | P73: 3 | Q73: A — Doorstep (≤5 km) | R73: 0 | S73: 37 | T73: Cambridge, international curriculum | U73: Cambridge, international curriculum, Life skills, confidence, leadership, Interest and passion-led learning | V73: I feel the curriculum of the school is very good and it helps the kids to grow up as a very confident, responsible and passionate individual.
A74: 64 | B74: Zahan Shamirulla | C74: LKG | D74: 2025-12-15 | E74: Software · DB · Relevantz IT | F74: Software Engineer · Analyst · TCS | G74: IT and software | H74: IT and software | I74: ₹15–30 L | J74: 16–38 | K74: Medium | L74: Medium | M74: Low | O74: Sithalapakkam | P74: 12 | Q74: C — Commutable (10–15 km) | R74: 0 | S74: 17 | T74: Not stated / general | U74: Not stated / general | V74: For better future
A75: 65 | B75: Sierra Akira | C75: LKG | D75: 2025-12-16 | E75: Private service · Senior Manager - Business Intelligence · Tata Consultancy Services | F75: Private service · Associate Director - AI Labs · Tiger Analytics | G75: Business owner | H75: Other | I75: ₹80 L and above | J75: 65–150 | K75: Medium | L75: Low | M75: Low | O75: Sithalapakkam | P75: 12 | Q75: C — Commutable (10–15 km) | R75: 0 | S75: 17 | T75: Holistic, all-round development | U75: Holistic, all-round development, Life skills, confidence, leadership, Recommendation and reputation | V75: Focusing on children holistic learning, independent interests, focused on children overall growth.My family friend kid studies here and suggested the lifestyle …
A76: 66 | B76: C V Toshika | C76: LKG | D76: 2025-12-22 | E76: IT · IT · Fiserv | F76: IT · Lead · NPCI | G76: IT and software | H76: IT and software | I76: ₹30–50 L | J76: 26–53 | K76: Medium | L76: Low | M76: Low | O76: Siruseri | P76: 6 | Q76: B — Near (5–10 km) | R76: 4 (Marigold) | S76: 14 | T76: Child-centric, individual attention | U76: Child-centric, individual attention, Experiential, hands-on learning, Values, nurturing environment and inclusion, Life skills, confidence, leadership | V76: We are seeking HLC as a learning centre for our child because of its child-centric approach that values curiosity, creativity, and emotional well-being alongsid…
A77: 67 | B77: Vedanth AK | C77: LKG | D77: 2025-12-26 | E77: IT Professional · Tech Lead · Fiserv India | F77: IT Professional · Associate Source Code Promoter · Ensono Technologies | G77: IT and software | H77: IT and software | I77: ₹30–50 L | J77: 26–55 | K77: Medium | L77: Low | M77: Low | O77: Perumbakkam | P77: 9 | Q77: B — Near (5–10 km) | R77: 1 (Oxygen Urban) | S77: 51 | T77: Cambridge, international curriculum | U77: Cambridge, international curriculum | V77: I gone through the school's website; the way child getting learning here is interesting and the focus here is on curriculum and other too. It's aligning with th…
A78: 68 | B78: Lia Runith | C78: LKG | D78: 2025-12-29 | E78: IT - software · Senior Technical Solutions Engineer · Data Bricks | F78: Textile Designer · Design Consultant · Self Employed | G78: IT and software | H78: Management and consulting | I78: ₹30–50 L | J78: 26–55 | K78: Medium | L78: Low | M78: Low | O78: Thalambur | P78: 3 | Q78: A — Doorstep (≤5 km) | R78: 0 | S78: 37 | T78: Experiential, hands-on learning | U78: Experiential, hands-on learning, Values, nurturing environment and inclusion, Cambridge, international curriculum | V78: An inclusive environment, driving curiosity, identifying and nurturing the kids areas of interest to drive learning with interest than mere curriculum and build…
A79: 69 | B79: Dhashvanth | C79: LKG | D79: 2025-12-30 | E79: — | F79: — | G79: Not stated | H79: Not stated | I79: Not determinable | J79: — | K79: — | L79: Low | M79: Low | O79: Not clear | P79: — | Q79: U — Not determinable | R79: 0 | S79: 0 | T79: Not stated / general | U79: Not stated / general
A80: 70 | B80: Githansh | C80: LKG | D80: 2025-12-30 | E80: Self Employed · Partner · Partner | F80: Self employed · Founder · Own company | G80: Business owner | H80: Business owner | I80: ₹50–80 L | J80: 30–100 | K80: Medium | L80: Low | M80: Low | O80: Madipakkam | P80: 15 | Q80: C — Commutable (10–15 km) | R80: 0 | S80: 2 | T80: Not stated / general | U80: Not stated / general | V80: Good place
A81: 71 | B81: Iniya M | C81: LKG | D81: 2025-12-31 | E81: IT · Proejct Co-ordinator · TechMahindra | F81: Housewife · Homemaker · Home | G81: IT and software | H81: Homemaker | I81: Below ₹15 L | J81: 8–18 | K81: Low | L81: Low | M81: Low | O81: Thalambur | P81: 3 | Q81: A — Doorstep (≤5 km) | R81: 0 | S81: 37 | T81: Proximity and convenience | U81: Proximity and convenience | V81: Near to my Location and got a good name for the school
A82: 72 | B82: Laya S A | C82: LKG | D82: 2026-01-05 | E82: Network engineer · Vice president · Bny technology pvt ltd | F82: Home maker · Not applicable · Not applicable | G82: Engineering (non-IT) | H82: Homemaker | I82: ₹80 L and above | J82: 60–125 | K82: Medium | L82: Medium | M82: Medium | O82: Padur | P82: 7 | Q82: B — Near (5–10 km) | R82: 7 (Pacifica Aurum) | S82: 14 | T82: Values, nurturing environment and inclusion | U82: Values, nurturing environment and inclusion, Interest and passion-led learning | V82: We believe HLC is idealogically aligned with how we wanted to raise our kid with right amount of education plus other nurturing of talent that gets the best in …
A83: 73 | B83: Ayra Parry | C83: LKG | D83: 2026-01-05 | E83: Software Engineer · Senior Test Lead · Ilink Digital Systems | F83: Software Engineer · Senior Associate · Cognizant | G83: IT and software | H83: IT and software | I83: ₹30–50 L | J83: 26–55 | K83: Medium | L83: Medium | M83: Medium | O83: Not clear | P83: — | Q83: U — Not determinable | R83: 0 | S83: 0 | T83: Experiential, hands-on learning | U83: Experiential, hands-on learning, Values, nurturing environment and inclusion | V83: We feel HLC will nurture our child’s curiosity, values, and foundational skills effectively.
A84: 74 | B84: Shiv Ariyan A | C84: LKG | D84: 2026-01-06 | E84: Business · Director · Amethyst Homes Pvt Limited | F84: Teacher · Teacher · Amethyst International School | G84: Business owner | H84: Teaching and academia | I84: ₹30–50 L | J84: 19–60 | K84: Medium | L84: Low | M84: High | O84: Karanai | P84: 1 | Q84: A — Doorstep (≤5 km) | R84: 3 (Amethyst) | S84: 13 | T84: Values, nurturing environment and inclusion | U84: Values, nurturing environment and inclusion, Interest and passion-led learning | V84: I think HLC will help nurture my child's interest and passion for acquiring knowledge.
A85: 75 | B85: Dhashvanth | C85: LKG | D85: 2026-01-06 | E85: Software Architect · Software Architect · IBM | F85: HomeMaker · NA · NA | G85: IT and software | H85: Homemaker | I85: ₹50–80 L | J85: 36–68 | K85: Medium | L85: Medium | M85: Medium | O85: Pallikaranai | P85: 12 | Q85: C — Commutable (10–15 km) | R85: 0 | S85: 6 | T85: Recommendation and reputation | U85: Recommendation and reputation | V85: I heard they are doing good
A86: 76 | B86: Daksha Brinda | C86: LKG | D86: 2026-01-12 | E86: Data Scientist · Co-founder · Earthmetry | F86: Manager - Operations Research · Manager · United Airlines | G86: Business owner | H86: Management and consulting | I86: ₹80 L and above | J86: 68–135 | K86: Medium | L86: Low | M86: Low | O86: Sholinganallur | P86: 6 | Q86: B — Near (5–10 km) | R86: 0 | S86: 22 | T86: Values, nurturing environment and inclusion | U86: Values, nurturing environment and inclusion | V86: I liked the idea of not inducing shame and respecting kids as mottos
A87: 77 | B87: Kriya | C87: LKG | D87: 2026-01-18 | E87: Engineer · Material Specialist · Renault Group | F87: Engineer · Tire Technologist · Apollo Tyres | G87: Engineering (non-IT) | H87: IT and software | I87: ₹30–50 L | J87: 29–63 | K87: Medium | L87: Medium | M87: Medium | O87: Thalambur | P87: 3 | Q87: A — Doorstep (≤5 km) | R87: 0 | S87: 37 | T87: Not stated / general | U87: Not stated / general | V87: Learning as a practice
A89: UKG · 21 applicants
A90: 78 | B90: Atharva Shankaran K | C90: UKG | D90: 2025-11-01 | E90: Employed · Manager · Ernst & Young | F90: Employed · Asst Manager · Northern Arc Capital Limited | G90: Management and consulting | H90: Management and consulting | I90: ₹50–80 L | J90: 36–70 | K90: Medium | L90: Low | M90: Low | O90: Besant Nagar | P90: 16 | Q90: D — Far (15–25 km) | R90: 1 (Academic Year) | S90: 0 | T90: Values, nurturing environment and inclusion | U90: Values, nurturing environment and inclusion | V90: When looking for a school for our son, we are looking for a balanced environment to provide formal education and personal growth. We look for an environment to …
A91: 79 | B91: Riaan Karthickeyan | C91: UKG | D91: 2025-11-01 | E91: Software Engineering Manager · Manager · Virtusa | F91: Home maker · Home maker · NA | G91: IT and software | H91: Homemaker | I91: ₹15–30 L | J91: 18–35 | K91: Medium | L91: Medium | M91: Medium | O91: Semmancheri | P91: 4 | Q91: A — Doorstep (≤5 km) | R91: 5 (Elegant Pinnacle) | S91: 10 | T91: Quality and standards of education | U91: Quality and standards of education | V91: Great school
A92: 80 | B92: Ashwin | C92: UKG | D92: 2025-11-01 | E92: Working in a Private Firm · Director-Account Management · Violin Technologies Private Limited | F92: Home Maker · NA · NA | G92: Management and consulting | H92: Homemaker | I92: ₹50–80 L | J92: 50–100 | K92: Medium | L92: Low | M92: Low | O92: Not clear | P92: — | Q92: U — Not determinable | R92: 0 | S92: 0 | T92: Cambridge, international curriculum | U92: Cambridge, international curriculum, Interest and passion-led learning | V92: The principle of HLC leaning center is more in line to my requirement for growing my child in his own interest and passion rather than focusing 100% only on cur…
A93: 81 | B93: Vihana Vijin | C93: UKG | D93: 2025-11-03 | E93: IT Professional · Principle Software Engineer · Zuora India Pvt Ltd | F93: IT Professional · Techinical Specialist · CitiusTech Healthcare Ltd | G93: IT and software | H93: IT and software | I93: ₹30–50 L | J93: 29–63 | K93: Medium | L93: Medium | M93: Medium | O93: Thalambur | P93: 3 | Q93: A — Doorstep (≤5 km) | R93: 0 | S93: 37 | T93: Stress-free, joyful learning | U93: Stress-free, joyful learning, Experiential, hands-on learning | V93: My kid is curious about exploring and learning things, rather than memorizing facts. She would love education only if it keeps her happy and meaningful. We sele…
A94: 82 | B94: Andhadhi D | C94: UKG | D94: 2025-11-03 | E94: IT consultant · Solution Architect and MDM Practice head · Isnia Technologies Pvt Ltd | F94: IT consultant · Senior Technical Lead · HCLTech | G94: IT and software | H94: IT and software | I94: ₹80 L and above | J94: 68–135 | K94: Medium | L94: Medium | M94: Medium | O94: Perumbakkam | P94: 9 | Q94: B — Near (5–10 km) | R94: 2 (Radiance) | S94: 51 | T94: Holistic, all-round development | U94: Holistic, all-round development, Interest and passion-led learning | V94: For a holistic approach and give equal importance to child's academy and her interest
A95: 83 | B95: AARYANSH KUMAR BEHARA | C95: UKG | D95: 2025-11-03 | E95: PRIVATE SECTOR EMPLOYEE · R&D PROJECT MANAGER · HITACHI | F95: SOFTWARE ENGINEER · MANAGER · CAPGEMINI | G95: Management and consulting | H95: IT and software | I95: ₹50–80 L | J95: 36–70 | K95: Medium | L95: Medium | M95: Medium | O95: Perumbakkam | P95: 9 | Q95: B — Near (5–10 km) | R95: 4 (Arasankalani) | S95: 51 | T95: Holistic, all-round development | U95: Holistic, all-round development, Quality and standards of education | V95: I am seeking HLC as a learning centre for my child because I believe it provides a strong balance between academic excellence and holistic development.
A96: 84 | B96: Arju Akshith A N | C96: UKG | D96: 2025-11-08 | E96: Private limited comapny · Senior Manager · KKN Energy pvt ltd | F96: IT · Engineer · Movate | G96: Management and consulting | H96: IT and software | I96: ₹50–80 L | J96: 38–75 | K96: Medium | L96: Low | M96: Low | O96: Kelambakkam | P96: 10 | Q96: B — Near (5–10 km) | R96: 0 | S96: 6 | T96: Holistic, all-round development | U96: Holistic, all-round development, Experiential, hands-on learning, Life skills, confidence, leadership, Interest and passion-led learning | V96: I want my child to have strong academics but also creative thinking, communication skills, emotional strength, and real-world understanding. HLC’s holistic lear…
A97: 85 | B97: Pugalini | C97: UKG | D97: 2025-11-12 | E97: IT Professional · Deputy Manager · Renault Nissan Tech | F97: Banking · Senior CSA · Indian Overseas Bank | G97: IT and software | H97: Banking and finance | I97: ₹30–50 L | J97: 29–63 | K97: Medium | L97: High | M97: High | O97: Mahindra World City | P97: 32 | Q97: E — Outside catchment (>25 km) | R97: 0 | S97: 0 | T97: Holistic, all-round development | U97: Holistic, all-round development, Values, nurturing environment and inclusion | V97: Considering the greater value assigned to holistic development than to academics
A98: 86 | B98: Nithila Gokula Kannan | C98: UKG | D98: 2025-11-13 | E98: Engineer · Project Management Lead · KLA | F98: Homemaker · NA · NA | G98: Engineering (non-IT) | H98: Homemaker | I98: ₹15–30 L | J98: 18–35 | K98: Medium | L98: Low | M98: Low | O98: Karanai | P98: 1 | Q98: A — Doorstep (≤5 km) | R98: 14 (Jones Cassia) | S98: 13 | T98: Values, nurturing environment and inclusion | U98: Values, nurturing environment and inclusion, Life skills, confidence, leadership, Interest and passion-led learning | V98: With the help of the information and testimonials available on the school website, I strongly believe that HLC will lay a strong foundation for our daughter's o…
A99: 87 | B99: Deeran Rajkumar | C99: UKG | D99: 2025-11-16 | E99: — | F99: — | G99: Not stated | H99: Not stated | I99: Not determinable | J99: — | K99: — | L99: Low | M99: Low | O99: Not clear | P99: — | Q99: U — Not determinable | R99: 0 | S99: 0 | T99: Not stated / general | U99: Not stated / general
A100: 88 | B100: SAI VIBISHA GV | C100: UKG | D100: 2025-11-17 | E100: Data Engineering Professional · Senior Data Engineer(IC) · Octillion Media India Private Limited | F100: Home Maker · - · - | G100: IT and software | H100: Homemaker | I100: Below ₹15 L | J100: 8–20 | K100: Medium | L100: Low | M100: Low | O100: Stated distance | P100: 6 | Q100: B — Near (5–10 km) | R100: 3 (Next Year) | S100: 0 | T100: Values, nurturing environment and inclusion | U100: Values, nurturing environment and inclusion, Life skills, confidence, leadership | V100: To identify my daughter’s interests and nurture them and be a catalyst in achieving her goals to become a good human and a good leader.
A101: 89 | B101: SAI VIBISHA GV | C101: UKG | D101: 2025-11-22 | E101: Data Engineering Professional · Manager, Data Engineering · Premion, LLC | F101: HOME MAKER · NA · NA | G101: IT and software | H101: Homemaker | I101: ₹15–30 L | J101: 18–35 | K101: Medium | L101: Low | M101: Low | O101: Sithalapakkam | P101: 12 | Q101: C — Commutable (10–15 km) | R101: 1 (Vinayagar) | S101: 17 | T101: Stress-free, joyful learning | U101: Stress-free, joyful learning, Values, nurturing environment and inclusion, Interest and passion-led learning | V101: We want our child to develop the passion for learning along with nurturing her own interests. And I don't want my child to go through the same path, which I too…
A102: 90 | B102: Pranav K P | C102: UKG | D102: 2025-11-22 | E102: Engineer · Assistant Manager · Stellantis | F102: IT Analyst · Expert · DHL | G102: Engineering (non-IT) | H102: IT and software | I102: ₹30–50 L | J102: 26–55 | K102: Medium | L102: Low | M102: Low | O102: Thalambur | P102: 3 | Q102: A — Doorstep (≤5 km) | R102: 8 (Dinesh Vihar) | S102: 37 | T102: Child-centric, individual attention | U102: Child-centric, individual attention, Stress-free, joyful learning, Experiential, hands-on learning, Values, nurturing environment and inclusion, Life skills, confidence, leadership, Interest and passion-led learning | V102: My son is empathetic and creative who thrives in an encouraging and positive environment. HLC's child - centric approach, focus on emotional wellbeing, and hand…
A103: 91 | B103: Vedhashree Lokesh Kumar | C103: UKG | D103: 2025-11-27 | E103: Private · Senior engineer · Renault Nissan Technologies businesses and center | F103: Private · Process development · Genpact | G103: Engineering (non-IT) | H103: Other | I103: ₹30–50 L | J103: 17–43 | K103: Medium | L103: Low | M103: Low | O103: Not clear | P103: — | Q103: U — Not determinable | R103: 0 | S103: 0 | T103: Not stated / general | U103: Not stated / general | V103: Unique way of teaching
A104: 92 | B104: JIYAARA M | C104: UKG | D104: 2025-11-28 | E104: SENIOR DESIGN ENGINEER · DESIGN ENGINEER · FORD TECHNOLOGY | F104: IT · SENIOR ASSOCIATE · COGNIZANT | G104: Engineering (non-IT) | H104: IT and software | I104: ₹30–50 L | J104: 17–45 | K104: Medium | L104: Medium | M104: Medium | O104: Thalambur | P104: 3 | Q104: A — Doorstep (≤5 km) | R104: 0 | S104: 37 | T104: Not stated / general | U104: Not stated / general | V104: Good exposure to my kid
A105: 93 | B105: Prasiddha V | C105: UKG | D105: 2025-12-17 | E105: IT Software developer · Project Manager · Intellect design arena | F105: Freelancer - Healer/ stay at home mom · Undertaking freelancing secretarial activities/ Intuitive healer/ chef · Freelancer | G105: IT and software | H105: Homemaker | I105: ₹15–30 L | J105: 18–35 | K105: Medium | L105: Medium | M105: Medium | O105: Navalur | P105: 5 | Q105: A — Doorstep (≤5 km) | R105: 9 (Olympia Opaline) | S105: 31 | T105: Experiential, hands-on learning | U105: Experiential, hands-on learning, Values, nurturing environment and inclusion, Cambridge, international curriculum, Life skills, confidence, leadership, Quality and standards of education, Interest and passion-led learning | V105: We're deeply rooted in our culture and values, and our parenting approach is about letting our child explore and learn through self-discovery rather than rigid,…
A106: 94 | B106: RAJIHAH FATHIMA | C106: UKG | D106: 2025-12-18 | E106: ARCHITECT · ARCHITECT · CHENNAI CITI CENTRE HOLDINGS PVT LTD | F106: HOUSE WIFE · HOUSE WIFE · HOUSE WIFE | G106: Media, design and arts | H106: Homemaker | I106: ₹50–80 L | J106: 36–68 | K106: Medium | L106: Medium | M106: Medium | O106: Not clear | P106: — | Q106: U — Not determinable | R106: 2 (Shifting) | S106: 0 | T106: Not stated / general | U106: Not stated / general | V106: FOR BETTER CAREER AND GOOD FUTURE
...

Sheet Method
A1: How the estimates were made — read before using
A2: Scope: the "just 2025-26" sheet of the application form (applications from November 2025), matched against the 2025-26 Master List of current students.
A3: Income: each parent's occupation and role are mapped to a salary range by seniority (for example CXO or Director ₹50–100 L; Manager or Lead ₹18–35 L; Engineer or Analyst ₹8–20 L; doctor ₹20–50 L; homemaker ₹0). Ranges rise about 20% for global MNC employers. Family range = father + mother. Confidence is Medium where a clear role or profession was stated, Low where only a generic label (for example "IT") was given. These are proxies, not facts.
A4: Profession 1 and 2: the father's and mother's occupation, role and employer standardised into twelve categories (for example IT and software, Banking and finance, Healthcare, Business owner, Homemaker). Where the occupation was vague, the employer decided it.
A5: Mobility: out-of-India likelihood is High where roles mention global, APAC, international or onsite work; Medium for global MNCs and IT-services managers; Low for business owners, doctors and local professions. Out-of-Chennai is High for defence, banking and government roles. Families mentioning relocation into Chennai are flagged separately.
A6: Distance: approximate road distance from HLC Karanai to the centre of the locality named in the address, or to the pincode area where no locality was found. No geocoding was used.
A7: Proximity grade: A Doorstep ≤5 km · B Near 5–10 km · C Commutable 10–15 km · D Far 15–25 km · E Outside catchment >25 km · U not determinable.
A8: Existing HLC families: an applicant is matched to current students whose address shares the same community or apartment name (a distinctive two-word name, or a rare word). Matches are probable, not certain.
A9: Why HLC: free-text answers were tagged against twelve themes by keywords. An answer can carry several themes; "Primary reason" is the first theme matched.
A10: Privacy: phone numbers, e-mails and parents' names are excluded. Income and mobility estimates are for internal planning only and must never be shared with families or used to treat applicants differently.
