Workbook

Sheet ReadMe
B2: AY 2027-28 Enrollment & Fund What-If Dashboard
B3: Built from your uploaded AY 27-28 financials. All figures in ₹ (INR).
B5: How to use
B6: 1. Go to the Inputs tab. Pick a scenario (Pessimistic / Realistic / Optimistic) in the yellow cell at the top — every other sheet updates instantly.
B7: 2. Every blue number on Inputs is editable — grade-wise new-joiner counts and their per-grade optimistic/pessimistic swing %, contribution % and its swing, fees, expenses, collection efficiency, cost variance, and fund balances.
B8: 3. The Dashboard tab shows the headline P&L, cash flow and fund position for whichever scenario is selected, plus a side-by-side comparison of all three scenarios and a chart.
B9: 4. The Calculations tab is the engine — grade-by-grade math for all three scenarios. You normally won't need to edit it; everything you'd want to change lives on Inputs.
B11: Key modelling choices
B12: - New Joiners are now Max Capacity x Capture %, not a blanket swing. The 'New Joiners' numbers in your source file are actually the school's MAXIMUM SEAT CAPACITY per grade (per your correction) — so Optimistic = filling 100% of that capacity, and Realistic / Pessimistic are each Capacity x a per-grade Capture % (how much of capacity you realistically expect to fill). A bigger capacity number is harder to fully realize (e.g. LKG, and especially AS/Grade 11) on top of AS being the structurally harder grade to convert — both are reflected in lower default Capture % for AS than for Grade I. Every Capture % is editable per grade.
B13: - Returnable Contribution % (existing students, to the corpus/building fund) also gets its own pessimistic/optimistic range per grade, as a +/- percentage-point swing on the realistic %.
B14: - Contributions from existing students, and (optionally) the Advance from new joiners, are treated as a REFUNDABLE LIABILITY — they hit Cash Inflow and the Fund roll-forward, but are excluded from P&L revenue. No interest is accrued on this balance, matching your note that contributions are returnable without interest.
B15: - Whether the Advance from new joiners is returnable or not is a Yes/No toggle on Inputs (default: Yes / returnable) since your brief only confirmed the treatment for existing-student contributions.
... B29: Yellow fill = key scenario / toggle controls

Sheet Inputs
B1: Inputs & Assumptions
B2: Edit any blue cell. Grades are rows, so each grade can have its own new-joiner / contribution swing (no blanket %).
B4: Active Scenario | C4: Realistic | E4: Treat 'Advance per New Joiner' as returnable (liability), not revenue? | J4: Yes
B6: Grade-wise enrollment, fee, contribution & dropout assumptions
B7: Grade | C7: Existing Students | D7: Base Fee (₹, LAST year's) | E7: Fee Increase % (applied to Base Fee) | F7: New Joiners - Max Capacity (= Optimistic) | G7: New Joiners Realistic Capture % (of Max Capacity) | H7: New Joiners Pessimistic Capture % (of Max Capacity) | I7: Contribution % - Realistic (existing students) | J7: Contribution Pessimistic Δ (pp) | K7: Contribution Optimistic Δ (pp) | L7: Contribution per Student (₹) | M7: Advance per New Joiner (₹) | N7: Possible Dropouts - Realistic (existing students) | O7: Dropout Pessimistic Δ% (more dropouts) | P7: Dropout Optimistic Δ% (fewer dropouts)
B8: Pre-KG | C8: 0 | F8: 0 | G8: 0.7 | H8: 0.5 | J8: 0 | K8: 0 | N8: 0 | O8: 0 | P8: 0
B9: LKG | C9: 4 | D9: 210000 | E9: 0 | F9: 26 | G9: 0.7 | H9: 0.5 | I9: 0 | J9: 0 | K9: 0 | M9: 100000 | N9: 0 | O9: 0 | P9: 0
B10: UKG | C10: 15 | D10: 201000 | E10: 0 | F10: 15 | G10: 0.75 | H10: 0.55 | I10: 0 | J10: 0 | K10: 0 | M10: 100000 | N10: 0 | O10: 0 | P10: 0
B11: I | C11: 23 | D11: 217000 | E11: 0 | F11: 14 | G11: 0.8 | H11: 0.6 | I11: 0 | J11: 0 | K11: 0 | M11: 100000 | N11: 0 | O11: 0 | P11: 0
B12: II | C12: 33 | D12: 217000 | E12: 0.2 | F12: 0 | G12: 0.7 | H12: 0.5 | I12: 0 | J12: 0 | K12: 0 | M12: 100000 | N12: 5 | O12: 0.5 | P12: -0.4
B13: III | C13: 34 | D13: 227000 | E13: 0.2 | F13: 0 | G13: 0.7 | H13: 0.5 | I13: 0 | J13: 0 | K13: 0 | M13: 100000 | N13: 5 | O13: 0.5 | P13: -0.4
B14: IV | C14: 32 | D14: 232000 | E14: 0.2 | F14: 0 | G14: 0.7 | H14: 0.5 | I14: 0 | J14: 0 | K14: 0 | M14: 100000 | N14: 5 | O14: 0.5 | P14: -0.4
B15: V | C15: 31 | D15: 254000 | E15: 0.2 | F15: 1 | G15: 0.7 | H15: 0.5 | I15: 0 | J15: 0 | K15: 0 | M15: 100000 | N15: 5 | O15: 0.5 | P15: -0.4
B16: VI | C16: 31 | D16: 270000 | E16: 0.2 | F16: 1 | G16: 0.7 | H16: 0.5 | I16: 0.2 | J16: -0.1 | K16: 0.1 | L16: 200000 | M16: 100000 | N16: 3 | O16: 0.5 | P16: -0.4
B17: VII | C17: 27 | D17: 288000 | E17: 0.2 | F17: 3 | G17: 0.7 | H17: 0.5 | I17: 0.2 | J17: -0.1 | K17: 0.1 | L17: 200000 | M17: 100000 | N17: 2 | O17: 0.5 | P17: -0.4
B18: VIII | C18: 25 | D18: 304000 | E18: 0.2 | F18: 5 | G18: 0.65 | H18: 0.45 | I18: 0.3 | J18: -0.1 | K18: 0.1 | L18: 200000 | M18: 100000 | N18: 2 | O18: 0.5 | P18: -0.4
B19: IX | C19: 26 | D19: 319000 | E19: 0.2 | F19: 4 | G19: 0.65 | H19: 0.45 | I19: 0.3 | J19: -0.1 | K19: 0.1 | L19: 200000 | M19: 100000 | N19: 1 | O19: 0.5 | P19: -0.4
B20: X | C20: 30 | D20: 332000 | E20: 0.2 | F20: 0 | G20: 0.7 | H20: 0.5 | I20: 0.2 | J20: -0.1 | K20: 0.1 | L20: 200000 | M20: 100000 | N20: 0 | O20: 0 | P20: 0
B21: AS | C21: 26 | D21: 294000 | E21: 0.2 | F21: 34 | G21: 0.5 | H21: 0.3 | I21: 0.1 | J21: -0.1 | K21: 0.1 | L21: 200000 | M21: 100000 | N21: 0 | O21: 0 | P21: 0
B22: A2 | C22: 29 | D22: 306000 | E22: 0.2 | F22: 1 | G22: 0.7 | H22: 0.5 | I22: 0 | J22: 0 | K22: 0 | M22: 100000 | N22: 0 | O22: 0 | P22: 0
B23: Total | C23: =SUM(C8:C22) -> 366 | F23: =SUM(F8:F22) -> 104 | N23: =SUM(N8:N22) -> 28
B25: Annual operating expenses (AY 2027-28 budget)
B26: Expense item | C26: Annual Amount (₹)
B27: Teacher salaries | C27: 57969300
B28: Rent | C28: 2750000
B29: Other core operating expenses | C29: 24347100
B30: Cambridge affiliation | C30: 1069196
B31: Safety / essential maintenance | C31: 2500000
B32: Property purchase loan servicing | C32: 13045454
B33: Growth marketing | C33: 5000000
B34: Additional / discretionary maintenance | C34: 2500000
B35: International obligations | C35: 4200000
B36: Miscellaneous Expenses | C36: =11338105/3 -> 3779368.3
B37: Total Operating Expenses | C37: =SUM(C27:C36) -> 1.1716042e+08
B39: Scenario overlays — overall dials
B40: The three Swing Multiplier columns are your single overall control per scenario: raise/lower one number here and every grade's New Joiner / Contribution / Dropout assumption (set on the table above) scales together, in proportion. 1.0 = the per-grade defaults above; 1.5 = 50% more aggressive; 0.5 = half as aggressive. NOTE the New Joiners multiplier is wired differently from the other two: New Joiners is now capacity-based (Optimistic = 100% of Max Capacity, fixed, so its multiplier cell is unused), and the multiplier instead scales the REALISTIC and PESSIMISTIC Capture % — i.e. Realistic's New Joiners multiplier IS active here, unlike Contribution/Dropout where Realistic is the fixed baseline and only Pessimistic/Optimistic scale. Cells with no effect for a given scenario are left white (not yellow) below. Fee Collection Efficiency % and Cost Variance % are a separate, cash/expense-only lever — they do NOT move New Joiners, Contribution % or Dropouts.
B41: Scenario | C41: Fee Collection Efficiency % (cash only) | D41: Cost Variance % (vs. budget) | E41: New Joiners Swing Multiplier (overall) | F41: Contribution Swing Multiplier (overall) | G41: Dropout Swing Multiplier (overall)
B42: Pessimistic | C42: 0.92 | D42: 0.03 | E42: 1 | F42: 1 | G42: 1
B43: Realistic | C43: 0.97 | D43: 0 | E43: 1 | F43: 1 | G43: 1
B44: Optimistic | C44: 0.99 | D44: -0.02 | E44: 1 | F44: 1 | G44: 1
B46: Returnable fund (corpus) balances
B47: Opening Balance of Returnable Fund, 1-Apr-2027 (₹) — locked at ₹0: AY 2027-28 is the FIRST year this contribution is being collected, so no prior balance exists. | F47: 0
B48: Refunds Paid to Leaving Students during AY 2027-28 (₹) — should also be ₹0: since this is the first year of collection, no departing student (including Possible Dropouts) could have contributed in a prior year, so none are owed a refund yet. | F48: 0
B51: Targeted retention scholarship (merit-cum-means, third party as transactional proxy)
B52: Rather than lowering the fee increase for everyone, a limited pool of at-risk families is offered a subsidized increase through a discreet, third-party-administered merit-cum-means scholarship. The third party is a transactional pass-through only -- the school bears the cost exactly as if it gave the discount directly. Only students who actually take up the scholarship pay the Subsidized Fee Increase % below; every other student keeps paying the full Fee Increase % on the grade table above -- there is no school-wide discount. The Target Pool below is spread across grades in the same proportion as the Possible Dropouts (Realistic) column above, and is automatically capped, per grade and per scenario, at however many students are actually projected to drop out there -- so the scholarship can never show more students 'retained' than were ever at risk of leaving.
B53: Subsidized Fee Increase % (for scholarship-retained students only) | F53: 0.13
B55: Scenario | C55: Target Pool to Retain (count, before capping by modelled dropouts)
B56: Pessimistic | C56: 15
B57: Realistic | C57: 30
B58: Optimistic | C58: 35

Sheet Dashboard
B1: AY 2027-28 What-If Dashboard
B2: Enrollment, returnable contributions, cash flow & P&L — scenario planning
B4: Active Scenario: | C4: =Inputs!$C$4 -> Realistic | E4: (change it on the Inputs tab — every number below updates)
B6: Total Cash Inflow | E6: Total Cash Outflow | H6: Net Cash Flow | K6: P&L Net Surplus / (Deficit) | N6: Revenue Impact of Fee Increase | Q6: Returnable Fund — Closing Balance
B7: =CHOOSE(MATCH(Inputs!$C$4,{"Pessimistic","Realistic","Optimistic"},0),Calculations!C96,Calculations!D96,Calculations!E96) -> 1.4300524e+08 | E7: =CHOOSE(MATCH(Inputs!$C$4,{"Pessimistic","Realistic","Optimistic"},0),Calculations!C100,Calculations!D100,Calculations!E100) -> 1.1716042e+08 | H7: =CHOOSE(MATCH(Inputs!$C$4,{"Pessimistic","Realistic","Optimistic"},0),Calculations!C101,Calculations!D101,Calculations!E101) -> 25844826 | K7: =CHOOSE(MATCH(Inputs!$C$4,{"Pessimistic","Realistic","Optimistic"},0),Calculations!C107,Calculations!D107,Calculations!E107) -> 15937772 | N7: =CHOOSE(MATCH(Inputs!$C$4,{"Pessimistic","Realistic","Optimistic"},0),Calculations!C112,Calculations!D112,Calculations!E112) -> 17251590 | Q7: =CHOOSE(MATCH(Inputs!$C$4,{"Pessimistic","Realistic","Optimistic"},0),Calculations!C117,Calculations!D117,Calculations!E117) -> 13900000
B11: Scenario Comparison — P&L & Cash Flow
B12: Metric | C12: Pessimistic | D12: Realistic | E12: Optimistic
B13: New Joiners (count) | C13: =Calculations!C86 -> 48 | D13: =Calculations!D86 -> 68 | E13: =Calculations!E86 -> 104
B14: Possible Dropouts - Before Scholarship (count) | C14: =Calculations!C87 -> 45 | D14: =Calculations!D87 -> 28 | E14: =Calculations!E87 -> 17
B15: Retained via Targeted Scholarship (count) | C15: =Calculations!C88 -> 17 | D15: =Calculations!D88 -> 28 | E15: =Calculations!E88 -> 17
B16: Possible Dropouts - After Scholarship / Actual (count) | C16: =Calculations!C89 -> 28 | D16: =Calculations!D89 -> 0 | E16: =Calculations!E89 -> 0
B17: Total Students | C17: =Calculations!C90 -> 386 | D17: =Calculations!D90 -> 434 | E17: =Calculations!E90 -> 470
B18: Tuition Fee Revenue (₹, accrual) | C18: =Calculations!C91 -> 119411930 | D18: =Calculations!D91 -> 133098190 | E18: =Calculations!E91 -> 143879330
B19: Tuition Fee Cash Collected (₹) | C19: =Calculations!C93 -> 1.0985898e+08 | D19: =Calculations!D93 -> 1.2910524e+08 | E19: =Calculations!E93 -> 1.4244054e+08
B20: Returnable Contribution Collected (₹) | C20: =Calculations!C94 -> 3580000 | D20: =Calculations!D94 -> 7100000 | E20: =Calculations!E94 -> 10400000
B21: Advance from New Joiners Collected (₹) | C21: =Calculations!C95 -> 4800000 | D21: =Calculations!D95 -> 6800000 | E21: =Calculations!E95 -> 10400000
B22: Total Cash Inflow (₹) | C22: =Calculations!C96 -> 1.1823898e+08 | D22: =Calculations!D96 -> 1.4300524e+08 | E22: =Calculations!E96 -> 1.6324054e+08
B23: Total Cash Outflow (₹) | C23: =Calculations!C100 -> 1.2067523e+08 | D23: =Calculations!D100 -> 1.1716042e+08 | E23: =Calculations!E100 -> 1.1481721e+08
B24: Net Cash Flow (₹) | C24: =Calculations!C101 -> -2436255.3 | D24: =Calculations!D101 -> 25844826 | E24: =Calculations!E101 -> 48423327
B25: P&L Total Revenue (₹) | C25: =Calculations!C105 -> 119411930 | D25: =Calculations!D105 -> 133098190 | E25: =Calculations!E105 -> 143879330
B26: P&L Total Operating Expenses (₹) | C26: =Calculations!C106 -> 1.2067523e+08 | D26: =Calculations!D106 -> 1.1716042e+08 | E26: =Calculations!E106 -> 1.1481721e+08
B27: P&L Net Surplus / (Deficit) (₹) | C27: =Calculations!C107 -> -1263300.9 | D27: =Calculations!D107 -> 15937772 | E27: =Calculations!E107 -> 29062120
B28: Fee-Increase Breakeven Dropout Threshold (count, fixed) | C28: =Calculations!C109 -> 54 | D28: =Calculations!D109 -> 54 | E28: =Calculations!E109 -> 54
B29: Headroom vs Breakeven Dropouts (count, after scholarship) | C29: =Calculations!C110 -> 26 | D29: =Calculations!D110 -> 54 | E29: =Calculations!E110 -> 54
B30: Revenue from Scholarship-Retained Students (₹) | C30: =Calculations!C111 -> 4792330 | D30: =Calculations!D111 -> 7868190 | E30: =Calculations!E111 -> 4792330
B31: Revenue Impact of Fee Increase vs No-Increase (₹, net of scholarship) | C31: =Calculations!C112 -> 9086530 | D31: =Calculations!D112 -> 17251590 | E31: =Calculations!E112 -> 17442130
B32: Returnable Fund — Closing Balance (₹) | C32: =Calculations!C117 -> 8380000 | D32: =Calculations!D117 -> 13900000 | E32: =Calculations!E117 -> 20800000
B35: Grade-wise Detail — Active Scenario
B36: Grade | C36: Existing Students | D36: New Joiners | E36: Total Students | F36: Tuition Fee Revenue (₹) | G36: Contribution % | H36: Contribution Collected (₹) | I36: Advance Collected (₹) | J36: Possible Dropouts (after scholarship)
B37: =CHOOSE(MATCH(Inputs!$C$4,{"Pessimistic","Realistic","Optimistic"},0),Calculations!B6,Calculations!B26,Calculations!B46) -> Pre-KG | C37: =CHOOSE(MATCH(Inputs!$C$4,{"Pessimistic","Realistic","Optimistic"},0),Calculations!C6,Calculations!C26,Calculations!C46) -> 0 | D37: =CHOOSE(MATCH(Inputs!$C$4,{"Pessimistic","Realistic","Optimistic"},0),Calculations!D6,Calculations!D26,Calculations!D46) -> 0 | E37: =CHOOSE(MATCH(Inputs!$C$4,{"Pessimistic","Realistic","Optimistic"},0),Calculations!E6,Calculations!E26,Calculations!E46) -> 0 | F37: =CHOOSE(MATCH(Inputs!$C$4,{"Pessimistic","Realistic","Optimistic"},0),Calculations!F6,Calculations!F26,Calculations!F46) -> 0 | G37: =CHOOSE(MATCH(Inputs!$C$4,{"Pessimistic","Realistic","Optimistic"},0),Calculations!G6,Calculations!G26,Calculations!G46) -> 0 | H37: =CHOOSE(MATCH(Inputs!$C$4,{"Pessimistic","Realistic","Optimistic"},0),Calculations!H6,Calculations!H26,Calculations!H46) -> 0 | I37: =CHOOSE(MATCH(Inputs!$C$4,{"Pessimistic","Realistic","Optimistic"},0),Calculations!I6,Calculations!I26,Calculations!I46) -> 0 | J37: =CHOOSE(MATCH(Inputs!$C$4,{"Pessimistic","Realistic","Optimistic"},0),Calculations!L6,Calculations!L26,Calculations!L46) -> 0
B38: =CHOOSE(MATCH(Inputs!$C$4,{"Pessimistic","Realistic","Optimistic"},0),Calculations!B7,Calculations!B27,Calculations!B47) -> LKG | C38: =CHOOSE(MATCH(Inputs!$C$4,{"Pessimistic","Realistic","Optimistic"},0),Calculations!C7,Calculations!C27,Calculations!C47) -> 4 | D38: =CHOOSE(MATCH(Inputs!$C$4,{"Pessimistic","Realistic","Optimistic"},0),Calculations!D7,Calculations!D27,Calculations!D47) -> 18 | E38: =CHOOSE(MATCH(Inputs!$C$4,{"Pessimistic","Realistic","Optimistic"},0),Calculations!E7,Calculations!E27,Calculations!E47) -> 22 | F38: =CHOOSE(MATCH(Inputs!$C$4,{"Pessimistic","Realistic","Optimistic"},0),Calculations!F7,Calculations!F27,Calculations!F47) -> 4620000 | G38: =CHOOSE(MATCH(Inputs!$C$4,{"Pessimistic","Realistic","Optimistic"},0),Calculations!G7,Calculations!G27,Calculations!G47) -> 0 | H38: =CHOOSE(MATCH(Inputs!$C$4,{"Pessimistic","Realistic","Optimistic"},0),Calculations!H7,Calculations!H27,Calculations!H47) -> 0 | I38: =CHOOSE(MATCH(Inputs!$C$4,{"Pessimistic","Realistic","Optimistic"},0),Calculations!I7,Calculations!I27,Calculations!I47) -> 1800000 | J38: =CHOOSE(MATCH(Inputs!$C$4,{"Pessimistic","Realistic","Optimistic"},0),Calculations!L7,Calculations!L27,Calculations!L47) -> 0
B39: =CHOOSE(MATCH(Inputs!$C$4,{"Pessimistic","Realistic","Optimistic"},0),Calculations!B8,Calculations!B28,Calculations!B48) -> UKG | C39: =CHOOSE(MATCH(Inputs!$C$4,{"Pessimistic","Realistic","Optimistic"},0),Calculations!C8,Calculations!C28,Calculations!C48) -> 15 | D39: =CHOOSE(MATCH(Inputs!$C$4,{"Pessimistic","Realistic","Optimistic"},0),Calculations!D8,Calculations!D28,Calculations!D48) -> 11 | E39: =CHOOSE(MATCH(Inputs!$C$4,{"Pessimistic","Realistic","Optimistic"},0),Calculations!E8,Calculations!E28,Calculations!E48) -> 26 | F39: =CHOOSE(MATCH(Inputs!$C$4,{"Pessimistic","Realistic","Optimistic"},0),Calculations!F8,Calculations!F28,Calculations!F48) -> 5226000 | G39: =CHOOSE(MATCH(Inputs!$C$4,{"Pessimistic","Realistic","Optimistic"},0),Calculations!G8,Calculations!G28,Calculations!G48) -> 0 | H39: =CHOOSE(MATCH(Inputs!$C$4,{"Pessimistic","Realistic","Optimistic"},0),Calculations!H8,Calculations!H28,Calculations!H48) -> 0 | I39: =CHOOSE(MATCH(Inputs!$C$4,{"Pessimistic","Realistic","Optimistic"},0),Calculations!I8,Calculations!I28,Calculations!I48) -> 1100000 | J39: =CHOOSE(MATCH(Inputs!$C$4,{"Pessimistic","Realistic","Optimistic"},0),Calculations!L8,Calculations!L28,Calculations!L48) -> 0
B40: =CHOOSE(MATCH(Inputs!$C$4,{"Pessimistic","Realistic","Optimistic"},0),Calculations!B9,Calculations!B29,Calculations!B49) -> I | C40: =CHOOSE(MATCH(Inputs!$C$4,{"Pessimistic","Realistic","Optimistic"},0),Calculations!C9,Calculations!C29,Calculations!C49) -> 23 | D40: =CHOOSE(MATCH(Inputs!$C$4,{"Pessimistic","Realistic","Optimistic"},0),Calculations!D9,Calculations!D29,Calculations!D49) -> 11 | E40: =CHOOSE(MATCH(Inputs!$C$4,{"Pessimistic","Realistic","Optimistic"},0),Calculations!E9,Calculations!E29,Calculations!E49) -> 34 | F40: =CHOOSE(MATCH(Inputs!$C$4,{"Pessimistic","Realistic","Optimistic"},0),Calculations!F9,Calculations!F29,Calculations!F49) -> 7378000 | G40: =CHOOSE(MATCH(Inputs!$C$4,{"Pessimistic","Realistic","Optimistic"},0),Calculations!G9,Calculations!G29,Calculations!G49) -> 0 | H40: =CHOOSE(MATCH(Inputs!$C$4,{"Pessimistic","Realistic","Optimistic"},0),Calculations!H9,Calculations!H29,Calculations!H49) -> 0 | I40: =CHOOSE(MATCH(Inputs!$C$4,{"Pessimistic","Realistic","Optimistic"},0),Calculations!I9,Calculations!I29,Calculations!I49) -> 1100000 | J40: =CHOOSE(MATCH(Inputs!$C$4,{"Pessimistic","Realistic","Optimistic"},0),Calculations!L9,Calculations!L29,Calculations!L49) -> 0
B41: =CHOOSE(MATCH(Inputs!$C$4,{"Pessimistic","Realistic","Optimistic"},0),Calculations!B10,Calculations!B30,Calculations!B50) -> II | C41: =CHOOSE(MATCH(Inputs!$C$4,{"Pessimistic","Realistic","Optimistic"},0),Calculations!C10,Calculations!C30,Calculations!C50) -> 33 | D41: =CHOOSE(MATCH(Inputs!$C$4,{"Pessimistic","Realistic","Optimistic"},0),Calculations!D10,Calculations!D30,Calculations!D50) -> 0 | E41: =CHOOSE(MATCH(Inputs!$C$4,{"Pessimistic","Realistic","Optimistic"},0),Calculations!E10,Calculations!E30,Calculations!E50) -> 33 | F41: =CHOOSE(MATCH(Inputs!$C$4,{"Pessimistic","Realistic","Optimistic"},0),Calculations!F10,Calculations!F30,Calculations!F50) -> 8517250 | G41: =CHOOSE(MATCH(Inputs!$C$4,{"Pessimistic","Realistic","Optimistic"},0),Calculations!G10,Calculations!G30,Calculations!G50) -> 0 | H41: =CHOOSE(MATCH(Inputs!$C$4,{"Pessimistic","Realistic","Optimistic"},0),Calculations!H10,Calculations!H30,Calculations!H50) -> 0 | I41: =CHOOSE(MATCH(Inputs!$C$4,{"Pessimistic","Realistic","Optimistic"},0),Calculations!I10,Calculations!I30,Calculations!I50) -> 0 | J41: =CHOOSE(MATCH(Inputs!$C$4,{"Pessimistic","Realistic","Optimistic"},0),Calculations!L10,Calculations!L30,Calculations!L50) -> 0
B42: =CHOOSE(MATCH(Inputs!$C$4,{"Pessimistic","Realistic","Optimistic"},0),Calculations!B11,Calculations!B31,Calculations!B51) -> III | C42: =CHOOSE(MATCH(Inputs!$C$4,{"Pessimistic","Realistic","Optimistic"},0),Calculations!C11,Calculations!C31,Calculations!C51) -> 34 | D42: =CHOOSE(MATCH(Inputs!$C$4,{"Pessimistic","Realistic","Optimistic"},0),Calculations!D11,Calculations!D31,Calculations!D51) -> 0 | E42: =CHOOSE(MATCH(Inputs!$C$4,{"Pessimistic","Realistic","Optimistic"},0),Calculations!E11,Calculations!E31,Calculations!E51) -> 34 | F42: =CHOOSE(MATCH(Inputs!$C$4,{"Pessimistic","Realistic","Optimistic"},0),Calculations!F11,Calculations!F31,Calculations!F51) -> 9182150 | G42: =CHOOSE(MATCH(Inputs!$C$4,{"Pessimistic","Realistic","Optimistic"},0),Calculations!G11,Calculations!G31,Calculations!G51) -> 0 | H42: =CHOOSE(MATCH(Inputs!$C$4,{"Pessimistic","Realistic","Optimistic"},0),Calculations!H11,Calculations!H31,Calculations!H51) -> 0 | I42: =CHOOSE(MATCH(Inputs!$C$4,{"Pessimistic","Realistic","Optimistic"},0),Calculations!I11,Calculations!I31,Calculations!I51) -> 0 | J42: =CHOOSE(MATCH(Inputs!$C$4,{"Pessimistic","Realistic","Optimistic"},0),Calculations!L11,Calculations!L31,Calculations!L51) -> 0
B43: =CHOOSE(MATCH(Inputs!$C$4,{"Pessimistic","Realistic","Optimistic"},0),Calculations!B12,Calculations!B32,Calculations!B52) -> IV | C43: =CHOOSE(MATCH(Inputs!$C$4,{"Pessimistic","Realistic","Optimistic"},0),Calculations!C12,Calculations!C32,Calculations!C52) -> 32 | D43: =CHOOSE(MATCH(Inputs!$C$4,{"Pessimistic","Realistic","Optimistic"},0),Calculations!D12,Calculations!D32,Calculations!D52) -> 0 | E43: =CHOOSE(MATCH(Inputs!$C$4,{"Pessimistic","Realistic","Optimistic"},0),Calculations!E12,Calculations!E32,Calculations!E52) -> 32 | F43: =CHOOSE(MATCH(Inputs!$C$4,{"Pessimistic","Realistic","Optimistic"},0),Calculations!F12,Calculations!F32,Calculations!F52) -> 8827600 | G43: =CHOOSE(MATCH(Inputs!$C$4,{"Pessimistic","Realistic","Optimistic"},0),Calculations!G12,Calculations!G32,Calculations!G52) -> 0 | H43: =CHOOSE(MATCH(Inputs!$C$4,{"Pessimistic","Realistic","Optimistic"},0),Calculations!H12,Calculations!H32,Calculations!H52) -> 0 | I43: =CHOOSE(MATCH(Inputs!$C$4,{"Pessimistic","Realistic","Optimistic"},0),Calculations!I12,Calculations!I32,Calculations!I52) -> 0 | J43: =CHOOSE(MATCH(Inputs!$C$4,{"Pessimistic","Realistic","Optimistic"},0),Calculations!L12,Calculations!L32,Calculations!L52) -> 0
B44: =CHOOSE(MATCH(Inputs!$C$4,{"Pessimistic","Realistic","Optimistic"},0),Calculations!B13,Calculations!B33,Calculations!B53) -> V | C44: =CHOOSE(MATCH(Inputs!$C$4,{"Pessimistic","Realistic","Optimistic"},0),Calculations!C13,Calculations!C33,Calculations!C53) -> 31 | D44: =CHOOSE(MATCH(Inputs!$C$4,{"Pessimistic","Realistic","Optimistic"},0),Calculations!D13,Calculations!D33,Calculations!D53) -> 1 | E44: =CHOOSE(MATCH(Inputs!$C$4,{"Pessimistic","Realistic","Optimistic"},0),Calculations!E13,Calculations!E33,Calculations!E53) -> 32 | F44: =CHOOSE(MATCH(Inputs!$C$4,{"Pessimistic","Realistic","Optimistic"},0),Calculations!F13,Calculations!F33,Calculations!F53) -> 9664700 | G44: =CHOOSE(MATCH(Inputs!$C$4,{"Pessimistic","Realistic","Optimistic"},0),Calculations!G13,Calculations!G33,Calculations!G53) -> 0 | H44: =CHOOSE(MATCH(Inputs!$C$4,{"Pessimistic","Realistic","Optimistic"},0),Calculations!H13,Calculations!H33,Calculations!H53) -> 0 | I44: =CHOOSE(MATCH(Inputs!$C$4,{"Pessimistic","Realistic","Optimistic"},0),Calculations!I13,Calculations!I33,Calculations!I53) -> 100000 | J44: =CHOOSE(MATCH(Inputs!$C$4,{"Pessimistic","Realistic","Optimistic"},0),Calculations!L13,Calculations!L33,Calculations!L53) -> 0
B45: =CHOOSE(MATCH(Inputs!$C$4,{"Pessimistic","Realistic","Optimistic"},0),Calculations!B14,Calculations!B34,Calculations!B54) -> VI | C45: =CHOOSE(MATCH(Inputs!$C$4,{"Pessimistic","Realistic","Optimistic"},0),Calculations!C14,Calculations!C34,Calculations!C54) -> 31 | D45: =CHOOSE(MATCH(Inputs!$C$4,{"Pessimistic","Realistic","Optimistic"},0),Calculations!D14,Calculations!D34,Calculations!D54) -> 1 | E45: =CHOOSE(MATCH(Inputs!$C$4,{"Pessimistic","Realistic","Optimistic"},0),Calculations!E14,Calculations!E34,Calculations!E54) -> 32 | F45: =CHOOSE(MATCH(Inputs!$C$4,{"Pessimistic","Realistic","Optimistic"},0),Calculations!F14,Calculations!F34,Calculations!F54) -> 10311300 | G45: =CHOOSE(MATCH(Inputs!$C$4,{"Pessimistic","Realistic","Optimistic"},0),Calculations!G14,Calculations!G34,Calculations!G54) -> 0.2 | H45: =CHOOSE(MATCH(Inputs!$C$4,{"Pessimistic","Realistic","Optimistic"},0),Calculations!H14,Calculations!H34,Calculations!H54) -> 1240000 | I45: =CHOOSE(MATCH(Inputs!$C$4,{"Pessimistic","Realistic","Optimistic"},0),Calculations!I14,Calculations!I34,Calculations!I54) -> 100000 | J45: =CHOOSE(MATCH(Inputs!$C$4,{"Pessimistic","Realistic","Optimistic"},0),Calculations!L14,Calculations!L34,Calculations!L54) -> 0
B46: =CHOOSE(MATCH(Inputs!$C$4,{"Pessimistic","Realistic","Optimistic"},0),Calculations!B15,Calculations!B35,Calculations!B55) -> VII | C46: =CHOOSE(MATCH(Inputs!$C$4,{"Pessimistic","Realistic","Optimistic"},0),Calculations!C15,Calculations!C35,Calculations!C55) -> 27 | D46: =CHOOSE(MATCH(Inputs!$C$4,{"Pessimistic","Realistic","Optimistic"},0),Calculations!D15,Calculations!D35,Calculations!D55) -> 2 | E46: =CHOOSE(MATCH(Inputs!$C$4,{"Pessimistic","Realistic","Optimistic"},0),Calculations!E15,Calculations!E35,Calculations!E55) -> 29 | F46: =CHOOSE(MATCH(Inputs!$C$4,{"Pessimistic","Realistic","Optimistic"},0),Calculations!F15,Calculations!F35,Calculations!F55) -> 9982080 | G46: =CHOOSE(MATCH(Inputs!$C$4,{"Pessimistic","Realistic","Optimistic"},0),Calculations!G15,Calculations!G35,Calculations!G55) -> 0.2 | H46: =CHOOSE(MATCH(Inputs!$C$4,{"Pessimistic","Realistic","Optimistic"},0),Calculations!H15,Calculations!H35,Calculations!H55) -> 1080000 | I46: =CHOOSE(MATCH(Inputs!$C$4,{"Pessimistic","Realistic","Optimistic"},0),Calculations!I15,Calculations!I35,Calculations!I55) -> 200000 | J46: =CHOOSE(MATCH(Inputs!$C$4,{"Pessimistic","Realistic","Optimistic"},0),Calculations!L15,Calculations!L35,Calculations!L55) -> 0
B47: =CHOOSE(MATCH(Inputs!$C$4,{"Pessimistic","Realistic","Optimistic"},0),Calculations!B16,Calculations!B36,Calculations!B56) -> VIII | C47: =CHOOSE(MATCH(Inputs!$C$4,{"Pessimistic","Realistic","Optimistic"},0),Calculations!C16,Calculations!C36,Calculations!C56) -> 25 | D47: =CHOOSE(MATCH(Inputs!$C$4,{"Pessimistic","Realistic","Optimistic"},0),Calculations!D16,Calculations!D36,Calculations!D56) -> 3 | E47: =CHOOSE(MATCH(Inputs!$C$4,{"Pessimistic","Realistic","Optimistic"},0),Calculations!E16,Calculations!E36,Calculations!E56) -> 28 | F47: =CHOOSE(MATCH(Inputs!$C$4,{"Pessimistic","Realistic","Optimistic"},0),Calculations!F16,Calculations!F36,Calculations!F56) -> 10171840 | G47: =CHOOSE(MATCH(Inputs!$C$4,{"Pessimistic","Realistic","Optimistic"},0),Calculations!G16,Calculations!G36,Calculations!G56) -> 0.3 | H47: =CHOOSE(MATCH(Inputs!$C$4,{"Pessimistic","Realistic","Optimistic"},0),Calculations!H16,Calculations!H36,Calculations!H56) -> 1500000 | I47: =CHOOSE(MATCH(Inputs!$C$4,{"Pessimistic","Realistic","Optimistic"},0),Calculations!I16,Calculations!I36,Calculations!I56) -> 300000 | J47: =CHOOSE(MATCH(Inputs!$C$4,{"Pessimistic","Realistic","Optimistic"},0),Calculations!L16,Calculations!L36,Calculations!L56) -> 0
B48: =CHOOSE(MATCH(Inputs!$C$4,{"Pessimistic","Realistic","Optimistic"},0),Calculations!B17,Calculations!B37,Calculations!B57) -> IX | C48: =CHOOSE(MATCH(Inputs!$C$4,{"Pessimistic","Realistic","Optimistic"},0),Calculations!C17,Calculations!C37,Calculations!C57) -> 26 | D48: =CHOOSE(MATCH(Inputs!$C$4,{"Pessimistic","Realistic","Optimistic"},0),Calculations!D17,Calculations!D37,Calculations!D57) -> 3 | E48: =CHOOSE(MATCH(Inputs!$C$4,{"Pessimistic","Realistic","Optimistic"},0),Calculations!E17,Calculations!E37,Calculations!E57) -> 29 | F48: =CHOOSE(MATCH(Inputs!$C$4,{"Pessimistic","Realistic","Optimistic"},0),Calculations!F17,Calculations!F37,Calculations!F57) -> 11078870 | G48: =CHOOSE(MATCH(Inputs!$C$4,{"Pessimistic","Realistic","Optimistic"},0),Calculations!G17,Calculations!G37,Calculations!G57) -> 0.3 | H48: =CHOOSE(MATCH(Inputs!$C$4,{"Pessimistic","Realistic","Optimistic"},0),Calculations!H17,Calculations!H37,Calculations!H57) -> 1560000 | I48: =CHOOSE(MATCH(Inputs!$C$4,{"Pessimistic","Realistic","Optimistic"},0),Calculations!I17,Calculations!I37,Calculations!I57) -> 300000 | J48: =CHOOSE(MATCH(Inputs!$C$4,{"Pessimistic","Realistic","Optimistic"},0),Calculations!L17,Calculations!L37,Calculations!L57) -> 0
... B51: =CHOOSE(MATCH(Inputs!$C$4,{"Pessimistic","Realistic","Optimistic"},0),Calculations!B20,Calculations!B40,Calculations!B60) -> A2 | C51: =CHOOSE(MATCH(Inputs!$C$4,{"Pessimistic","Realistic","Optimistic"},0),Calculations!C20,Calculations!C40,Calculations!C60) -> 29 | D51: =CHOOSE(MATCH(Inputs!$C$4,{"Pessimistic","Realistic","Optimistic"},0),Calculations!D20,Calculations!D40,Calculations!D60) -> 1 | E51: =CHOOSE(MATCH(Inputs!$C$4,{"Pessimistic","Realistic","Optimistic"},0),Calculations!E20,Calculations!E40,Calculations!E60) -> 30 | F51: =CHOOSE(MATCH(Inputs!$C$4,{"Pessimistic","Realistic","Optimistic"},0),Calculations!F20,Calculations!F40,Calculations!F60) -> 11016000 | G51: =CHOOSE(MATCH(Inputs!$C$4,{"Pessimistic","Realistic","Optimistic"},0),Calculations!G20,Calculations!G40,Calculations!G60) -> 0 | H51: =CHOOSE(MATCH(Inputs!$C$4,{"Pessimistic","Realistic","Optimistic"},0),Calculations!H20,Calculations!H40,Calculations!H60) -> 0 | I51: =CHOOSE(MATCH(Inputs!$C$4,{"Pessimistic","Realistic","Optimistic"},0),Calculations!I20,Calculations!I40,Calculations!I60) -> 100000 | J51: =CHOOSE(MATCH(Inputs!$C$4,{"Pessimistic","Realistic","Optimistic"},0),Calculations!L20,Calculations!L40,Calculations!L60) -> 0
B52: Total | C52: =SUM(C37:C51) -> 366 | D52: =SUM(D37:D51) -> 68 | E52: =SUM(E37:E51) -> 434 | F52: =SUM(F37:F51) -> 133098190 | H52: =SUM(H37:H51) -> 7100000 | I52: =SUM(I37:I51) -> 6800000 | J52: =SUM(J37:J51) -> 0

Sheet Calculations
B1: Calculations — Scenario Engine
B2: Grade-by-grade math for each scenario. Everything here is a formula pulling from Inputs — normally no need to edit.
B4: PESSIMISTIC SCENARIO
B5: Grade | C5: Existing Students | D5: New Joiners | E5: Total Students | F5: Tuition Fee Revenue (₹) | G5: Contribution % | H5: Contribution Collected (₹) | I5: Advance Collected (₹) | J5: Possible Dropouts (before scholarship) | K5: Retained via Scholarship | L5: Possible Dropouts (after scholarship)
B6: =Inputs!B8 -> Pre-KG | C6: =Inputs!C8 -> 0 | D6: =MIN(Inputs!F8,MAX(0,ROUND(Inputs!F8*Inputs!H8*Inputs!$E$42,0))) -> 0 | E6: =C6-L6+D6 -> 0 | F6: =(C6-J6+D6)*Inputs!D8*(1+Inputs!E8)+K6*Inputs!D8*(1+Inputs!$F$53) -> 0 | G6: =MIN(1,MAX(0,Inputs!I8+Inputs!J8*Inputs!$F$42)) -> 0 | H6: =(C6-L6)*G6*Inputs!L8 -> 0 | I6: =D6*Inputs!M8 -> 0 | J6: =MAX(0,ROUND(Inputs!N8*(1+Inputs!O8*Inputs!$G$42),0)) -> 0 | K6: =MIN(J6,IFERROR(ROUND(Inputs!$C$56*Inputs!N8/Inputs!$N$23,0),0)) -> 0 | L6: =J6-K6 -> 0
B7: =Inputs!B9 -> LKG | C7: =Inputs!C9 -> 4 | D7: =MIN(Inputs!F9,MAX(0,ROUND(Inputs!F9*Inputs!H9*Inputs!$E$42,0))) -> 13 | E7: =C7-L7+D7 -> 17 | F7: =(C7-J7+D7)*Inputs!D9*(1+Inputs!E9)+K7*Inputs!D9*(1+Inputs!$F$53) -> 3570000 | G7: =MIN(1,MAX(0,Inputs!I9+Inputs!J9*Inputs!$F$42)) -> 0 | H7: =(C7-L7)*G7*Inputs!L9 -> 0 | I7: =D7*Inputs!M9 -> 1300000 | J7: =MAX(0,ROUND(Inputs!N9*(1+Inputs!O9*Inputs!$G$42),0)) -> 0 | K7: =MIN(J7,IFERROR(ROUND(Inputs!$C$56*Inputs!N9/Inputs!$N$23,0),0)) -> 0 | L7: =J7-K7 -> 0
B8: =Inputs!B10 -> UKG | C8: =Inputs!C10 -> 15 | D8: =MIN(Inputs!F10,MAX(0,ROUND(Inputs!F10*Inputs!H10*Inputs!$E$42,0))) -> 8 | E8: =C8-L8+D8 -> 23 | F8: =(C8-J8+D8)*Inputs!D10*(1+Inputs!E10)+K8*Inputs!D10*(1+Inputs!$F$53) -> 4623000 | G8: =MIN(1,MAX(0,Inputs!I10+Inputs!J10*Inputs!$F$42)) -> 0 | H8: =(C8-L8)*G8*Inputs!L10 -> 0 | I8: =D8*Inputs!M10 -> 800000 | J8: =MAX(0,ROUND(Inputs!N10*(1+Inputs!O10*Inputs!$G$42),0)) -> 0 | K8: =MIN(J8,IFERROR(ROUND(Inputs!$C$56*Inputs!N10/Inputs!$N$23,0),0)) -> 0 | L8: =J8-K8 -> 0
B9: =Inputs!B11 -> I | C9: =Inputs!C11 -> 23 | D9: =MIN(Inputs!F11,MAX(0,ROUND(Inputs!F11*Inputs!H11*Inputs!$E$42,0))) -> 8 | E9: =C9-L9+D9 -> 31 | F9: =(C9-J9+D9)*Inputs!D11*(1+Inputs!E11)+K9*Inputs!D11*(1+Inputs!$F$53) -> 6727000 | G9: =MIN(1,MAX(0,Inputs!I11+Inputs!J11*Inputs!$F$42)) -> 0 | H9: =(C9-L9)*G9*Inputs!L11 -> 0 | I9: =D9*Inputs!M11 -> 800000 | J9: =MAX(0,ROUND(Inputs!N11*(1+Inputs!O11*Inputs!$G$42),0)) -> 0 | K9: =MIN(J9,IFERROR(ROUND(Inputs!$C$56*Inputs!N11/Inputs!$N$23,0),0)) -> 0 | L9: =J9-K9 -> 0
B10: =Inputs!B12 -> II | C10: =Inputs!C12 -> 33 | D10: =MIN(Inputs!F12,MAX(0,ROUND(Inputs!F12*Inputs!H12*Inputs!$E$42,0))) -> 0 | E10: =C10-L10+D10 -> 28 | F10: =(C10-J10+D10)*Inputs!D12*(1+Inputs!E12)+K10*Inputs!D12*(1+Inputs!$F$53) -> 7245630 | G10: =MIN(1,MAX(0,Inputs!I12+Inputs!J12*Inputs!$F$42)) -> 0 | H10: =(C10-L10)*G10*Inputs!L12 -> 0 | I10: =D10*Inputs!M12 -> 0 | J10: =MAX(0,ROUND(Inputs!N12*(1+Inputs!O12*Inputs!$G$42),0)) -> 8 | K10: =MIN(J10,IFERROR(ROUND(Inputs!$C$56*Inputs!N12/Inputs!$N$23,0),0)) -> 3 | L10: =J10-K10 -> 5
B11: =Inputs!B13 -> III | C11: =Inputs!C13 -> 34 | D11: =MIN(Inputs!F13,MAX(0,ROUND(Inputs!F13*Inputs!H13*Inputs!$E$42,0))) -> 0 | E11: =C11-L11+D11 -> 29 | F11: =(C11-J11+D11)*Inputs!D13*(1+Inputs!E13)+K11*Inputs!D13*(1+Inputs!$F$53) -> 7851930 | G11: =MIN(1,MAX(0,Inputs!I13+Inputs!J13*Inputs!$F$42)) -> 0 | H11: =(C11-L11)*G11*Inputs!L13 -> 0 | I11: =D11*Inputs!M13 -> 0 | J11: =MAX(0,ROUND(Inputs!N13*(1+Inputs!O13*Inputs!$G$42),0)) -> 8 | K11: =MIN(J11,IFERROR(ROUND(Inputs!$C$56*Inputs!N13/Inputs!$N$23,0),0)) -> 3 | L11: =J11-K11 -> 5
B12: =Inputs!B14 -> IV | C12: =Inputs!C14 -> 32 | D12: =MIN(Inputs!F14,MAX(0,ROUND(Inputs!F14*Inputs!H14*Inputs!$E$42,0))) -> 0 | E12: =C12-L12+D12 -> 27 | F12: =(C12-J12+D12)*Inputs!D14*(1+Inputs!E14)+K12*Inputs!D14*(1+Inputs!$F$53) -> 7468080 | G12: =MIN(1,MAX(0,Inputs!I14+Inputs!J14*Inputs!$F$42)) -> 0 | H12: =(C12-L12)*G12*Inputs!L14 -> 0 | I12: =D12*Inputs!M14 -> 0 | J12: =MAX(0,ROUND(Inputs!N14*(1+Inputs!O14*Inputs!$G$42),0)) -> 8 | K12: =MIN(J12,IFERROR(ROUND(Inputs!$C$56*Inputs!N14/Inputs!$N$23,0),0)) -> 3 | L12: =J12-K12 -> 5
B13: =Inputs!B15 -> V | C13: =Inputs!C15 -> 31 | D13: =MIN(Inputs!F15,MAX(0,ROUND(Inputs!F15*Inputs!H15*Inputs!$E$42,0))) -> 1 | E13: =C13-L13+D13 -> 27 | F13: =(C13-J13+D13)*Inputs!D15*(1+Inputs!E15)+K13*Inputs!D15*(1+Inputs!$F$53) -> 8176260 | G13: =MIN(1,MAX(0,Inputs!I15+Inputs!J15*Inputs!$F$42)) -> 0 | H13: =(C13-L13)*G13*Inputs!L15 -> 0 | I13: =D13*Inputs!M15 -> 100000 | J13: =MAX(0,ROUND(Inputs!N15*(1+Inputs!O15*Inputs!$G$42),0)) -> 8 | K13: =MIN(J13,IFERROR(ROUND(Inputs!$C$56*Inputs!N15/Inputs!$N$23,0),0)) -> 3 | L13: =J13-K13 -> 5
B14: =Inputs!B16 -> VI | C14: =Inputs!C16 -> 31 | D14: =MIN(Inputs!F16,MAX(0,ROUND(Inputs!F16*Inputs!H16*Inputs!$E$42,0))) -> 1 | E14: =C14-L14+D14 -> 29 | F14: =(C14-J14+D14)*Inputs!D16*(1+Inputs!E16)+K14*Inputs!D16*(1+Inputs!$F$53) -> 9358200 | G14: =MIN(1,MAX(0,Inputs!I16+Inputs!J16*Inputs!$F$42)) -> 0.1 | H14: =(C14-L14)*G14*Inputs!L16 -> 560000 | I14: =D14*Inputs!M16 -> 100000 | J14: =MAX(0,ROUND(Inputs!N16*(1+Inputs!O16*Inputs!$G$42),0)) -> 5 | K14: =MIN(J14,IFERROR(ROUND(Inputs!$C$56*Inputs!N16/Inputs!$N$23,0),0)) -> 2 | L14: =J14-K14 -> 3
B15: =Inputs!B17 -> VII | C15: =Inputs!C17 -> 27 | D15: =MIN(Inputs!F17,MAX(0,ROUND(Inputs!F17*Inputs!H17*Inputs!$E$42,0))) -> 2 | E15: =C15-L15+D15 -> 27 | F15: =(C15-J15+D15)*Inputs!D17*(1+Inputs!E17)+K15*Inputs!D17*(1+Inputs!$F$53) -> 9311040 | G15: =MIN(1,MAX(0,Inputs!I17+Inputs!J17*Inputs!$F$42)) -> 0.1 | H15: =(C15-L15)*G15*Inputs!L17 -> 500000 | I15: =D15*Inputs!M17 -> 200000 | J15: =MAX(0,ROUND(Inputs!N17*(1+Inputs!O17*Inputs!$G$42),0)) -> 3 | K15: =MIN(J15,IFERROR(ROUND(Inputs!$C$56*Inputs!N17/Inputs!$N$23,0),0)) -> 1 | L15: =J15-K15 -> 2
B16: =Inputs!B18 -> VIII | C16: =Inputs!C18 -> 25 | D16: =MIN(Inputs!F18,MAX(0,ROUND(Inputs!F18*Inputs!H18*Inputs!$E$42,0))) -> 2 | E16: =C16-L16+D16 -> 25 | F16: =(C16-J16+D16)*Inputs!D18*(1+Inputs!E18)+K16*Inputs!D18*(1+Inputs!$F$53) -> 9098720 | G16: =MIN(1,MAX(0,Inputs!I18+Inputs!J18*Inputs!$F$42)) -> 0.2 | H16: =(C16-L16)*G16*Inputs!L18 -> 920000 | I16: =D16*Inputs!M18 -> 200000 | J16: =MAX(0,ROUND(Inputs!N18*(1+Inputs!O18*Inputs!$G$42),0)) -> 3 | K16: =MIN(J16,IFERROR(ROUND(Inputs!$C$56*Inputs!N18/Inputs!$N$23,0),0)) -> 1 | L16: =J16-K16 -> 2
B17: =Inputs!B19 -> IX | C17: =Inputs!C19 -> 26 | D17: =MIN(Inputs!F19,MAX(0,ROUND(Inputs!F19*Inputs!H19*Inputs!$E$42,0))) -> 2 | E17: =C17-L17+D17 -> 27 | F17: =(C17-J17+D17)*Inputs!D19*(1+Inputs!E19)+K17*Inputs!D19*(1+Inputs!$F$53) -> 10313270 | G17: =MIN(1,MAX(0,Inputs!I19+Inputs!J19*Inputs!$F$42)) -> 0.2 | H17: =(C17-L17)*G17*Inputs!L19 -> 1000000 | I17: =D17*Inputs!M19 -> 200000 | J17: =MAX(0,ROUND(Inputs!N19*(1+Inputs!O19*Inputs!$G$42),0)) -> 2 | K17: =MIN(J17,IFERROR(ROUND(Inputs!$C$56*Inputs!N19/Inputs!$N$23,0),0)) -> 1 | L17: =J17-K17 -> 1
... B20: =Inputs!B22 -> A2 | C20: =Inputs!C22 -> 29 | D20: =MIN(Inputs!F22,MAX(0,ROUND(Inputs!F22*Inputs!H22*Inputs!$E$42,0))) -> 1 | E20: =C20-L20+D20 -> 30 | F20: =(C20-J20+D20)*Inputs!D22*(1+Inputs!E22)+K20*Inputs!D22*(1+Inputs!$F$53) -> 11016000 | G20: =MIN(1,MAX(0,Inputs!I22+Inputs!J22*Inputs!$F$42)) -> 0 | H20: =(C20-L20)*G20*Inputs!L22 -> 0 | I20: =D20*Inputs!M22 -> 100000 | J20: =MAX(0,ROUND(Inputs!N22*(1+Inputs!O22*Inputs!$G$42),0)) -> 0 | K20: =MIN(J20,IFERROR(ROUND(Inputs!$C$56*Inputs!N22/Inputs!$N$23,0),0)) -> 0 | L20: =J20-K20 -> 0
B21: Total | C21: =SUM(C6:C20) -> 366 | D21: =SUM(D6:D20) -> 48 | E21: =SUM(E6:E20) -> 386 | F21: =SUM(F6:F20) -> 119411930 | H21: =SUM(H6:H20) -> 3580000 | I21: =SUM(I6:I20) -> 4800000 | J21: =SUM(J6:J20) -> 45 | K21: =SUM(K6:K20) -> 17 | L21: =SUM(L6:L20) -> 28
B24: REALISTIC SCENARIO
B25: Grade | C25: Existing Students | D25: New Joiners | E25: Total Students | F25: Tuition Fee Revenue (₹) | G25: Contribution % | H25: Contribution Collected (₹) | I25: Advance Collected (₹) | J25: Possible Dropouts (before scholarship) | K25: Retained via Scholarship | L25: Possible Dropouts (after scholarship)
B26: =Inputs!B8 -> Pre-KG | C26: =Inputs!C8 -> 0 | D26: =MIN(Inputs!F8,MAX(0,ROUND(Inputs!F8*Inputs!G8*Inputs!$E$43,0))) -> 0 | E26: =C26-L26+D26 -> 0 | F26: =(C26-J26+D26)*Inputs!D8*(1+Inputs!E8)+K26*Inputs!D8*(1+Inputs!$F$53) -> 0 | G26: =Inputs!I8 -> 0 | H26: =(C26-L26)*G26*Inputs!L8 -> 0 | I26: =D26*Inputs!M8 -> 0 | J26: =Inputs!N8 -> 0 | K26: =MIN(J26,IFERROR(ROUND(Inputs!$C$57*Inputs!N8/Inputs!$N$23,0),0)) -> 0 | L26: =J26-K26 -> 0
B27: =Inputs!B9 -> LKG | C27: =Inputs!C9 -> 4 | D27: =MIN(Inputs!F9,MAX(0,ROUND(Inputs!F9*Inputs!G9*Inputs!$E$43,0))) -> 18 | E27: =C27-L27+D27 -> 22 | F27: =(C27-J27+D27)*Inputs!D9*(1+Inputs!E9)+K27*Inputs!D9*(1+Inputs!$F$53) -> 4620000 | G27: =Inputs!I9 -> 0 | H27: =(C27-L27)*G27*Inputs!L9 -> 0 | I27: =D27*Inputs!M9 -> 1800000 | J27: =Inputs!N9 -> 0 | K27: =MIN(J27,IFERROR(ROUND(Inputs!$C$57*Inputs!N9/Inputs!$N$23,0),0)) -> 0 | L27: =J27-K27 -> 0
B28: =Inputs!B10 -> UKG | C28: =Inputs!C10 -> 15 | D28: =MIN(Inputs!F10,MAX(0,ROUND(Inputs!F10*Inputs!G10*Inputs!$E$43,0))) -> 11 | E28: =C28-L28+D28 -> 26 | F28: =(C28-J28+D28)*Inputs!D10*(1+Inputs!E10)+K28*Inputs!D10*(1+Inputs!$F$53) -> 5226000 | G28: =Inputs!I10 -> 0 | H28: =(C28-L28)*G28*Inputs!L10 -> 0 | I28: =D28*Inputs!M10 -> 1100000 | J28: =Inputs!N10 -> 0 | K28: =MIN(J28,IFERROR(ROUND(Inputs!$C$57*Inputs!N10/Inputs!$N$23,0),0)) -> 0 | L28: =J28-K28 -> 0
B29: =Inputs!B11 -> I | C29: =Inputs!C11 -> 23 | D29: =MIN(Inputs!F11,MAX(0,ROUND(Inputs!F11*Inputs!G11*Inputs!$E$43,0))) -> 11 | E29: =C29-L29+D29 -> 34 | F29: =(C29-J29+D29)*Inputs!D11*(1+Inputs!E11)+K29*Inputs!D11*(1+Inputs!$F$53) -> 7378000 | G29: =Inputs!I11 -> 0 | H29: =(C29-L29)*G29*Inputs!L11 -> 0 | I29: =D29*Inputs!M11 -> 1100000 | J29: =Inputs!N11 -> 0 | K29: =MIN(J29,IFERROR(ROUND(Inputs!$C$57*Inputs!N11/Inputs!$N$23,0),0)) -> 0 | L29: =J29-K29 -> 0
B30: =Inputs!B12 -> II | C30: =Inputs!C12 -> 33 | D30: =MIN(Inputs!F12,MAX(0,ROUND(Inputs!F12*Inputs!G12*Inputs!$E$43,0))) -> 0 | E30: =C30-L30+D30 -> 33 | F30: =(C30-J30+D30)*Inputs!D12*(1+Inputs!E12)+K30*Inputs!D12*(1+Inputs!$F$53) -> 8517250 | G30: =Inputs!I12 -> 0 | H30: =(C30-L30)*G30*Inputs!L12 -> 0 | I30: =D30*Inputs!M12 -> 0 | J30: =Inputs!N12 -> 5 | K30: =MIN(J30,IFERROR(ROUND(Inputs!$C$57*Inputs!N12/Inputs!$N$23,0),0)) -> 5 | L30: =J30-K30 -> 0
B31: =Inputs!B13 -> III | C31: =Inputs!C13 -> 34 | D31: =MIN(Inputs!F13,MAX(0,ROUND(Inputs!F13*Inputs!G13*Inputs!$E$43,0))) -> 0 | E31: =C31-L31+D31 -> 34 | F31: =(C31-J31+D31)*Inputs!D13*(1+Inputs!E13)+K31*Inputs!D13*(1+Inputs!$F$53) -> 9182150 | G31: =Inputs!I13 -> 0 | H31: =(C31-L31)*G31*Inputs!L13 -> 0 | I31: =D31*Inputs!M13 -> 0 | J31: =Inputs!N13 -> 5 | K31: =MIN(J31,IFERROR(ROUND(Inputs!$C$57*Inputs!N13/Inputs!$N$23,0),0)) -> 5 | L31: =J31-K31 -> 0
B32: =Inputs!B14 -> IV | C32: =Inputs!C14 -> 32 | D32: =MIN(Inputs!F14,MAX(0,ROUND(Inputs!F14*Inputs!G14*Inputs!$E$43,0))) -> 0 | E32: =C32-L32+D32 -> 32 | F32: =(C32-J32+D32)*Inputs!D14*(1+Inputs!E14)+K32*Inputs!D14*(1+Inputs!$F$53) -> 8827600 | G32: =Inputs!I14 -> 0 | H32: =(C32-L32)*G32*Inputs!L14 -> 0 | I32: =D32*Inputs!M14 -> 0 | J32: =Inputs!N14 -> 5 | K32: =MIN(J32,IFERROR(ROUND(Inputs!$C$57*Inputs!N14/Inputs!$N$23,0),0)) -> 5 | L32: =J32-K32 -> 0
B33: =Inputs!B15 -> V | C33: =Inputs!C15 -> 31 | D33: =MIN(Inputs!F15,MAX(0,ROUND(Inputs!F15*Inputs!G15*Inputs!$E$43,0))) -> 1 | E33: =C33-L33+D33 -> 32 | F33: =(C33-J33+D33)*Inputs!D15*(1+Inputs!E15)+K33*Inputs!D15*(1+Inputs!$F$53) -> 9664700 | G33: =Inputs!I15 -> 0 | H33: =(C33-L33)*G33*Inputs!L15 -> 0 | I33: =D33*Inputs!M15 -> 100000 | J33: =Inputs!N15 -> 5 | K33: =MIN(J33,IFERROR(ROUND(Inputs!$C$57*Inputs!N15/Inputs!$N$23,0),0)) -> 5 | L33: =J33-K33 -> 0
B34: =Inputs!B16 -> VI | C34: =Inputs!C16 -> 31 | D34: =MIN(Inputs!F16,MAX(0,ROUND(Inputs!F16*Inputs!G16*Inputs!$E$43,0))) -> 1 | E34: =C34-L34+D34 -> 32 | F34: =(C34-J34+D34)*Inputs!D16*(1+Inputs!E16)+K34*Inputs!D16*(1+Inputs!$F$53) -> 10311300 | G34: =Inputs!I16 -> 0.2 | H34: =(C34-L34)*G34*Inputs!L16 -> 1240000 | I34: =D34*Inputs!M16 -> 100000 | J34: =Inputs!N16 -> 3 | K34: =MIN(J34,IFERROR(ROUND(Inputs!$C$57*Inputs!N16/Inputs!$N$23,0),0)) -> 3 | L34: =J34-K34 -> 0
B35: =Inputs!B17 -> VII | C35: =Inputs!C17 -> 27 | D35: =MIN(Inputs!F17,MAX(0,ROUND(Inputs!F17*Inputs!G17*Inputs!$E$43,0))) -> 2 | E35: =C35-L35+D35 -> 29 | F35: =(C35-J35+D35)*Inputs!D17*(1+Inputs!E17)+K35*Inputs!D17*(1+Inputs!$F$53) -> 9982080 | G35: =Inputs!I17 -> 0.2 | H35: =(C35-L35)*G35*Inputs!L17 -> 1080000 | I35: =D35*Inputs!M17 -> 200000 | J35: =Inputs!N17 -> 2 | K35: =MIN(J35,IFERROR(ROUND(Inputs!$C$57*Inputs!N17/Inputs!$N$23,0),0)) -> 2 | L35: =J35-K35 -> 0
B36: =Inputs!B18 -> VIII | C36: =Inputs!C18 -> 25 | D36: =MIN(Inputs!F18,MAX(0,ROUND(Inputs!F18*Inputs!G18*Inputs!$E$43,0))) -> 3 | E36: =C36-L36+D36 -> 28 | F36: =(C36-J36+D36)*Inputs!D18*(1+Inputs!E18)+K36*Inputs!D18*(1+Inputs!$F$53) -> 10171840 | G36: =Inputs!I18 -> 0.3 | H36: =(C36-L36)*G36*Inputs!L18 -> 1500000 | I36: =D36*Inputs!M18 -> 300000 | J36: =Inputs!N18 -> 2 | K36: =MIN(J36,IFERROR(ROUND(Inputs!$C$57*Inputs!N18/Inputs!$N$23,0),0)) -> 2 | L36: =J36-K36 -> 0
B37: =Inputs!B19 -> IX | C37: =Inputs!C19 -> 26 | D37: =MIN(Inputs!F19,MAX(0,ROUND(Inputs!F19*Inputs!G19*Inputs!$E$43,0))) -> 3 | E37: =C37-L37+D37 -> 29 | F37: =(C37-J37+D37)*Inputs!D19*(1+Inputs!E19)+K37*Inputs!D19*(1+Inputs!$F$53) -> 11078870 | G37: =Inputs!I19 -> 0.3 | H37: =(C37-L37)*G37*Inputs!L19 -> 1560000 | I37: =D37*Inputs!M19 -> 300000 | J37: =Inputs!N19 -> 1 | K37: =MIN(J37,IFERROR(ROUND(Inputs!$C$57*Inputs!N19/Inputs!$N$23,0),0)) -> 1 | L37: =J37-K37 -> 0
... B40: =Inputs!B22 -> A2 | C40: =Inputs!C22 -> 29 | D40: =MIN(Inputs!F22,MAX(0,ROUND(Inputs!F22*Inputs!G22*Inputs!$E$43,0))) -> 1 | E40: =C40-L40+D40 -> 30 | F40: =(C40-J40+D40)*Inputs!D22*(1+Inputs!E22)+K40*Inputs!D22*(1+Inputs!$F$53) -> 11016000 | G40: =Inputs!I22 -> 0 | H40: =(C40-L40)*G40*Inputs!L22 -> 0 | I40: =D40*Inputs!M22 -> 100000 | J40: =Inputs!N22 -> 0 | K40: =MIN(J40,IFERROR(ROUND(Inputs!$C$57*Inputs!N22/Inputs!$N$23,0),0)) -> 0 | L40: =J40-K40 -> 0
B41: Total | C41: =SUM(C26:C40) -> 366 | D41: =SUM(D26:D40) -> 68 | E41: =SUM(E26:E40) -> 434 | F41: =SUM(F26:F40) -> 133098190 | H41: =SUM(H26:H40) -> 7100000 | I41: =SUM(I26:I40) -> 6800000 | J41: =SUM(J26:J40) -> 28 | K41: =SUM(K26:K40) -> 28 | L41: =SUM(L26:L40) -> 0
B44: OPTIMISTIC SCENARIO
B45: Grade | C45: Existing Students | D45: New Joiners | E45: Total Students | F45: Tuition Fee Revenue (₹) | G45: Contribution % | H45: Contribution Collected (₹) | I45: Advance Collected (₹) | J45: Possible Dropouts (before scholarship) | K45: Retained via Scholarship | L45: Possible Dropouts (after scholarship)
B46: =Inputs!B8 -> Pre-KG | C46: =Inputs!C8 -> 0 | D46: =Inputs!F8 -> 0 | E46: =C46-L46+D46 -> 0 | F46: =(C46-J46+D46)*Inputs!D8*(1+Inputs!E8)+K46*Inputs!D8*(1+Inputs!$F$53) -> 0 | G46: =MIN(1,MAX(0,Inputs!I8+Inputs!K8*Inputs!$F$44)) -> 0 | H46: =(C46-L46)*G46*Inputs!L8 -> 0 | I46: =D46*Inputs!M8 -> 0 | J46: =MAX(0,ROUND(Inputs!N8*(1+Inputs!P8*Inputs!$G$44),0)) -> 0 | K46: =MIN(J46,IFERROR(ROUND(Inputs!$C$58*Inputs!N8/Inputs!$N$23,0),0)) -> 0 | L46: =J46-K46 -> 0
B47: =Inputs!B9 -> LKG | C47: =Inputs!C9 -> 4 | D47: =Inputs!F9 -> 26 | E47: =C47-L47+D47 -> 30 | F47: =(C47-J47+D47)*Inputs!D9*(1+Inputs!E9)+K47*Inputs!D9*(1+Inputs!$F$53) -> 6300000 | G47: =MIN(1,MAX(0,Inputs!I9+Inputs!K9*Inputs!$F$44)) -> 0 | H47: =(C47-L47)*G47*Inputs!L9 -> 0 | I47: =D47*Inputs!M9 -> 2600000 | J47: =MAX(0,ROUND(Inputs!N9*(1+Inputs!P9*Inputs!$G$44),0)) -> 0 | K47: =MIN(J47,IFERROR(ROUND(Inputs!$C$58*Inputs!N9/Inputs!$N$23,0),0)) -> 0 | L47: =J47-K47 -> 0
B48: =Inputs!B10 -> UKG | C48: =Inputs!C10 -> 15 | D48: =Inputs!F10 -> 15 | E48: =C48-L48+D48 -> 30 | F48: =(C48-J48+D48)*Inputs!D10*(1+Inputs!E10)+K48*Inputs!D10*(1+Inputs!$F$53) -> 6030000 | G48: =MIN(1,MAX(0,Inputs!I10+Inputs!K10*Inputs!$F$44)) -> 0 | H48: =(C48-L48)*G48*Inputs!L10 -> 0 | I48: =D48*Inputs!M10 -> 1500000 | J48: =MAX(0,ROUND(Inputs!N10*(1+Inputs!P10*Inputs!$G$44),0)) -> 0 | K48: =MIN(J48,IFERROR(ROUND(Inputs!$C$58*Inputs!N10/Inputs!$N$23,0),0)) -> 0 | L48: =J48-K48 -> 0
B49: =Inputs!B11 -> I | C49: =Inputs!C11 -> 23 | D49: =Inputs!F11 -> 14 | E49: =C49-L49+D49 -> 37 | F49: =(C49-J49+D49)*Inputs!D11*(1+Inputs!E11)+K49*Inputs!D11*(1+Inputs!$F$53) -> 8029000 | G49: =MIN(1,MAX(0,Inputs!I11+Inputs!K11*Inputs!$F$44)) -> 0 | H49: =(C49-L49)*G49*Inputs!L11 -> 0 | I49: =D49*Inputs!M11 -> 1400000 | J49: =MAX(0,ROUND(Inputs!N11*(1+Inputs!P11*Inputs!$G$44),0)) -> 0 | K49: =MIN(J49,IFERROR(ROUND(Inputs!$C$58*Inputs!N11/Inputs!$N$23,0),0)) -> 0 | L49: =J49-K49 -> 0
B50: =Inputs!B12 -> II | C50: =Inputs!C12 -> 33 | D50: =Inputs!F12 -> 0 | E50: =C50-L50+D50 -> 33 | F50: =(C50-J50+D50)*Inputs!D12*(1+Inputs!E12)+K50*Inputs!D12*(1+Inputs!$F$53) -> 8547630 | G50: =MIN(1,MAX(0,Inputs!I12+Inputs!K12*Inputs!$F$44)) -> 0 | H50: =(C50-L50)*G50*Inputs!L12 -> 0 | I50: =D50*Inputs!M12 -> 0 | J50: =MAX(0,ROUND(Inputs!N12*(1+Inputs!P12*Inputs!$G$44),0)) -> 3 | K50: =MIN(J50,IFERROR(ROUND(Inputs!$C$58*Inputs!N12/Inputs!$N$23,0),0)) -> 3 | L50: =J50-K50 -> 0
B51: =Inputs!B13 -> III | C51: =Inputs!C13 -> 34 | D51: =Inputs!F13 -> 0 | E51: =C51-L51+D51 -> 34 | F51: =(C51-J51+D51)*Inputs!D13*(1+Inputs!E13)+K51*Inputs!D13*(1+Inputs!$F$53) -> 9213930 | G51: =MIN(1,MAX(0,Inputs!I13+Inputs!K13*Inputs!$F$44)) -> 0 | H51: =(C51-L51)*G51*Inputs!L13 -> 0 | I51: =D51*Inputs!M13 -> 0 | J51: =MAX(0,ROUND(Inputs!N13*(1+Inputs!P13*Inputs!$G$44),0)) -> 3 | K51: =MIN(J51,IFERROR(ROUND(Inputs!$C$58*Inputs!N13/Inputs!$N$23,0),0)) -> 3 | L51: =J51-K51 -> 0
B52: =Inputs!B14 -> IV | C52: =Inputs!C14 -> 32 | D52: =Inputs!F14 -> 0 | E52: =C52-L52+D52 -> 32 | F52: =(C52-J52+D52)*Inputs!D14*(1+Inputs!E14)+K52*Inputs!D14*(1+Inputs!$F$53) -> 8860080 | G52: =MIN(1,MAX(0,Inputs!I14+Inputs!K14*Inputs!$F$44)) -> 0 | H52: =(C52-L52)*G52*Inputs!L14 -> 0 | I52: =D52*Inputs!M14 -> 0 | J52: =MAX(0,ROUND(Inputs!N14*(1+Inputs!P14*Inputs!$G$44),0)) -> 3 | K52: =MIN(J52,IFERROR(ROUND(Inputs!$C$58*Inputs!N14/Inputs!$N$23,0),0)) -> 3 | L52: =J52-K52 -> 0
B53: =Inputs!B15 -> V | C53: =Inputs!C15 -> 31 | D53: =Inputs!F15 -> 1 | E53: =C53-L53+D53 -> 32 | F53: =(C53-J53+D53)*Inputs!D15*(1+Inputs!E15)+K53*Inputs!D15*(1+Inputs!$F$53) -> 9700260 | G53: =MIN(1,MAX(0,Inputs!I15+Inputs!K15*Inputs!$F$44)) -> 0 | H53: =(C53-L53)*G53*Inputs!L15 -> 0 | I53: =D53*Inputs!M15 -> 100000 | J53: =MAX(0,ROUND(Inputs!N15*(1+Inputs!P15*Inputs!$G$44),0)) -> 3 | K53: =MIN(J53,IFERROR(ROUND(Inputs!$C$58*Inputs!N15/Inputs!$N$23,0),0)) -> 3 | L53: =J53-K53 -> 0
B54: =Inputs!B16 -> VI | C54: =Inputs!C16 -> 31 | D54: =Inputs!F16 -> 1 | E54: =C54-L54+D54 -> 32 | F54: =(C54-J54+D54)*Inputs!D16*(1+Inputs!E16)+K54*Inputs!D16*(1+Inputs!$F$53) -> 10330200 | G54: =MIN(1,MAX(0,Inputs!I16+Inputs!K16*Inputs!$F$44)) -> 0.3 | H54: =(C54-L54)*G54*Inputs!L16 -> 1860000 | I54: =D54*Inputs!M16 -> 100000 | J54: =MAX(0,ROUND(Inputs!N16*(1+Inputs!P16*Inputs!$G$44),0)) -> 2 | K54: =MIN(J54,IFERROR(ROUND(Inputs!$C$58*Inputs!N16/Inputs!$N$23,0),0)) -> 2 | L54: =J54-K54 -> 0
B55: =Inputs!B17 -> VII | C55: =Inputs!C17 -> 27 | D55: =Inputs!F17 -> 3 | E55: =C55-L55+D55 -> 30 | F55: =(C55-J55+D55)*Inputs!D17*(1+Inputs!E17)+K55*Inputs!D17*(1+Inputs!$F$53) -> 10347840 | G55: =MIN(1,MAX(0,Inputs!I17+Inputs!K17*Inputs!$F$44)) -> 0.3 | H55: =(C55-L55)*G55*Inputs!L17 -> 1620000 | I55: =D55*Inputs!M17 -> 300000 | J55: =MAX(0,ROUND(Inputs!N17*(1+Inputs!P17*Inputs!$G$44),0)) -> 1 | K55: =MIN(J55,IFERROR(ROUND(Inputs!$C$58*Inputs!N17/Inputs!$N$23,0),0)) -> 1 | L55: =J55-K55 -> 0
B56: =Inputs!B18 -> VIII | C56: =Inputs!C18 -> 25 | D56: =Inputs!F18 -> 5 | E56: =C56-L56+D56 -> 30 | F56: =(C56-J56+D56)*Inputs!D18*(1+Inputs!E18)+K56*Inputs!D18*(1+Inputs!$F$53) -> 10922720 | G56: =MIN(1,MAX(0,Inputs!I18+Inputs!K18*Inputs!$F$44)) -> 0.4 | H56: =(C56-L56)*G56*Inputs!L18 -> 2000000 | I56: =D56*Inputs!M18 -> 500000 | J56: =MAX(0,ROUND(Inputs!N18*(1+Inputs!P18*Inputs!$G$44),0)) -> 1 | K56: =MIN(J56,IFERROR(ROUND(Inputs!$C$58*Inputs!N18/Inputs!$N$23,0),0)) -> 1 | L56: =J56-K56 -> 0
B57: =Inputs!B19 -> IX | C57: =Inputs!C19 -> 26 | D57: =Inputs!F19 -> 4 | E57: =C57-L57+D57 -> 30 | F57: =(C57-J57+D57)*Inputs!D19*(1+Inputs!E19)+K57*Inputs!D19*(1+Inputs!$F$53) -> 11461670 | G57: =MIN(1,MAX(0,Inputs!I19+Inputs!K19*Inputs!$F$44)) -> 0.4 | H57: =(C57-L57)*G57*Inputs!L19 -> 2080000 | I57: =D57*Inputs!M19 -> 400000 | J57: =MAX(0,ROUND(Inputs!N19*(1+Inputs!P19*Inputs!$G$44),0)) -> 1 | K57: =MIN(J57,IFERROR(ROUND(Inputs!$C$58*Inputs!N19/Inputs!$N$23,0),0)) -> 1 | L57: =J57-K57 -> 0
... B60: =Inputs!B22 -> A2 | C60: =Inputs!C22 -> 29 | D60: =Inputs!F22 -> 1 | E60: =C60-L60+D60 -> 30 | F60: =(C60-J60+D60)*Inputs!D22*(1+Inputs!E22)+K60*Inputs!D22*(1+Inputs!$F$53) -> 11016000 | G60: =MIN(1,MAX(0,Inputs!I22+Inputs!K22*Inputs!$F$44)) -> 0 | H60: =(C60-L60)*G60*Inputs!L22 -> 0 | I60: =D60*Inputs!M22 -> 100000 | J60: =MAX(0,ROUND(Inputs!N22*(1+Inputs!P22*Inputs!$G$44),0)) -> 0 | K60: =MIN(J60,IFERROR(ROUND(Inputs!$C$58*Inputs!N22/Inputs!$N$23,0),0)) -> 0 | L60: =J60-K60 -> 0
B61: Total | C61: =SUM(C46:C60) -> 366 | D61: =SUM(D46:D60) -> 104 | E61: =SUM(E46:E60) -> 470 | F61: =SUM(F46:F60) -> 143879330 | H61: =SUM(H46:H60) -> 10400000 | I61: =SUM(I46:I60) -> 10400000 | J61: =SUM(J46:J60) -> 17 | K61: =SUM(K46:K60) -> 17 | L61: =SUM(L46:L60) -> 0
B64: FEE-INCREASE BREAKEVEN (existing students, fixed reference)
B65: Grade | C65: Existing Students | D65: Fee Increase % | E65: Base Fee (₹, last year) | F65: Breakeven Dropout % | G65: Breakeven Dropout Count | H65: Revenue if Fee NOT Increased (₹) | I65: Revenue at Breakeven (₹, check)
B66: =Inputs!B8 -> Pre-KG | C66: =Inputs!C8 -> 0 | D66: =Inputs!E8 -> 0 | E66: =Inputs!D8 -> 0 | F66: =IFERROR(D66/(1+D66),0) -> 0 | G66: =ROUND(C66*F66,0) -> 0 | H66: =C66*E66 -> 0 | I66: =(C66-G66)*E66*(1+D66) -> 0
B67: =Inputs!B9 -> LKG | C67: =Inputs!C9 -> 4 | D67: =Inputs!E9 -> 0 | E67: =Inputs!D9 -> 210000 | F67: =IFERROR(D67/(1+D67),0) -> 0 | G67: =ROUND(C67*F67,0) -> 0 | H67: =C67*E67 -> 840000 | I67: =(C67-G67)*E67*(1+D67) -> 840000
B68: =Inputs!B10 -> UKG | C68: =Inputs!C10 -> 15 | D68: =Inputs!E10 -> 0 | E68: =Inputs!D10 -> 201000 | F68: =IFERROR(D68/(1+D68),0) -> 0 | G68: =ROUND(C68*F68,0) -> 0 | H68: =C68*E68 -> 3015000 | I68: =(C68-G68)*E68*(1+D68) -> 3015000
B69: =Inputs!B11 -> I | C69: =Inputs!C11 -> 23 | D69: =Inputs!E11 -> 0 | E69: =Inputs!D11 -> 217000 | F69: =IFERROR(D69/(1+D69),0) -> 0 | G69: =ROUND(C69*F69,0) -> 0 | H69: =C69*E69 -> 4991000 | I69: =(C69-G69)*E69*(1+D69) -> 4991000
B70: =Inputs!B12 -> II | C70: =Inputs!C12 -> 33 | D70: =Inputs!E12 -> 0.2 | E70: =Inputs!D12 -> 217000 | F70: =IFERROR(D70/(1+D70),0) -> 0.16666667 | G70: =ROUND(C70*F70,0) -> 6 | H70: =C70*E70 -> 7161000 | I70: =(C70-G70)*E70*(1+D70) -> 7030800
B71: =Inputs!B13 -> III | C71: =Inputs!C13 -> 34 | D71: =Inputs!E13 -> 0.2 | E71: =Inputs!D13 -> 227000 | F71: =IFERROR(D71/(1+D71),0) -> 0.16666667 | G71: =ROUND(C71*F71,0) -> 6 | H71: =C71*E71 -> 7718000 | I71: =(C71-G71)*E71*(1+D71) -> 7627200
B72: =Inputs!B14 -> IV | C72: =Inputs!C14 -> 32 | D72: =Inputs!E14 -> 0.2 | E72: =Inputs!D14 -> 232000 | F72: =IFERROR(D72/(1+D72),0) -> 0.16666667 | G72: =ROUND(C72*F72,0) -> 5 | H72: =C72*E72 -> 7424000 | I72: =(C72-G72)*E72*(1+D72) -> 7516800
B73: =Inputs!B15 -> V | C73: =Inputs!C15 -> 31 | D73: =Inputs!E15 -> 0.2 | E73: =Inputs!D15 -> 254000 | F73: =IFERROR(D73/(1+D73),0) -> 0.16666667 | G73: =ROUND(C73*F73,0) -> 5 | H73: =C73*E73 -> 7874000 | I73: =(C73-G73)*E73*(1+D73) -> 7924800
B74: =Inputs!B16 -> VI | C74: =Inputs!C16 -> 31 | D74: =Inputs!E16 -> 0.2 | E74: =Inputs!D16 -> 270000 | F74: =IFERROR(D74/(1+D74),0) -> 0.16666667 | G74: =ROUND(C74*F74,0) -> 5 | H74: =C74*E74 -> 8370000 | I74: =(C74-G74)*E74*(1+D74) -> 8424000
B75: =Inputs!B17 -> VII | C75: =Inputs!C17 -> 27 | D75: =Inputs!E17 -> 0.2 | E75: =Inputs!D17 -> 288000 | F75: =IFERROR(D75/(1+D75),0) -> 0.16666667 | G75: =ROUND(C75*F75,0) -> 5 | H75: =C75*E75 -> 7776000 | I75: =(C75-G75)*E75*(1+D75) -> 7603200
B76: =Inputs!B18 -> VIII | C76: =Inputs!C18 -> 25 | D76: =Inputs!E18 -> 0.2 | E76: =Inputs!D18 -> 304000 | F76: =IFERROR(D76/(1+D76),0) -> 0.16666667 | G76: =ROUND(C76*F76,0) -> 4 | H76: =C76*E76 -> 7600000 | I76: =(C76-G76)*E76*(1+D76) -> 7660800
B77: =Inputs!B19 -> IX | C77: =Inputs!C19 -> 26 | D77: =Inputs!E19 -> 0.2 | E77: =Inputs!D19 -> 319000 | F77: =IFERROR(D77/(1+D77),0) -> 0.16666667 | G77: =ROUND(C77*F77,0) -> 4 | H77: =C77*E77 -> 8294000 | I77: =(C77-G77)*E77*(1+D77) -> 8421600
... B80: =Inputs!B22 -> A2 | C80: =Inputs!C22 -> 29 | D80: =Inputs!E22 -> 0.2 | E80: =Inputs!D22 -> 306000 | F80: =IFERROR(D80/(1+D80),0) -> 0.16666667 | G80: =ROUND(C80*F80,0) -> 5 | H80: =C80*E80 -> 8874000 | I80: =(C80-G80)*E80*(1+D80) -> 8812800
B81: Total | C81: =SUM(C66:C80) -> 366 | G81: =SUM(G66:G80) -> 54 | H81: =SUM(H66:H80) -> 97541000 | I81: =SUM(I66:I80) -> 97589600
B84: SCENARIO SUMMARY — AY 2027-28
B85: Metric | C85: Pessimistic | D85: Realistic | E85: Optimistic
B86: New Joiners (count) | C86: =D21 -> 48 | D86: =D41 -> 68 | E86: =D61 -> 104
B87: Possible Dropouts - Before Scholarship (count) | C87: =J21 -> 45 | D87: =J41 -> 28 | E87: =J61 -> 17
B88: Retained via Targeted Scholarship (count) | C88: =K21 -> 17 | D88: =K41 -> 28 | E88: =K61 -> 17
B89: Possible Dropouts - After Scholarship / Actual (count) | C89: =L21 -> 28 | D89: =L41 -> 0 | E89: =L61 -> 0
B90: Total Students | C90: =E21 -> 386 | D90: =E41 -> 434 | E90: =E61 -> 470
B91: Tuition Fee Revenue (₹, accrual) | C91: =F21 -> 119411930 | D91: =F41 -> 133098190 | E91: =F61 -> 143879330
B92: Fee Collection Efficiency % | C92: =Inputs!$C$42 -> 0.92 | D92: =Inputs!$C$43 -> 0.97 | E92: =Inputs!$C$44 -> 0.99
B93: Tuition Fee Cash Collected (₹) | C93: =C91*C92 -> 1.0985898e+08 | D93: =D91*D92 -> 1.2910524e+08 | E93: =E91*E92 -> 1.4244054e+08
B94: Returnable Contribution Collected (₹) | C94: =H21 -> 3580000 | D94: =H41 -> 7100000 | E94: =H61 -> 10400000
B95: Advance from New Joiners Collected (₹) | C95: =I21 -> 4800000 | D95: =I41 -> 6800000 | E95: =I61 -> 10400000
B96: Total Cash Inflow (₹) | C96: =C93+C94+C95 -> 1.1823898e+08 | D96: =D93+D94+D95 -> 1.4300524e+08 | E96: =E93+E94+E95 -> 1.6324054e+08
B98: Total Operating Expenses — Budget (₹) | C98: =Inputs!$C$37 -> 1.1716042e+08 | D98: =Inputs!$C$37 -> 1.1716042e+08 | E98: =Inputs!$C$37 -> 1.1716042e+08
B99: Cost Variance % | C99: =Inputs!$D$42 -> 0.03 | D99: =Inputs!$D$43 -> 0 | E99: =Inputs!$D$44 -> -0.02
B100: Total Cash Outflow (₹) | C100: =C98*(1+C99) -> 1.2067523e+08 | D100: =D98*(1+D99) -> 1.1716042e+08 | E100: =E98*(1+E99) -> 1.1481721e+08
B101: Net Cash Flow (₹) | C101: =C96-C100 -> -2436255.3 | D101: =D96-D100 -> 25844826 | E101: =E96-E100 -> 48423327
B103: P&L — Tuition Fee Revenue (₹) | C103: =C91 -> 119411930 | D103: =D91 -> 133098190 | E103: =E91 -> 143879330
B104: P&L — Advance Revenue (₹, only if not returnable) | C104: =IF(Inputs!$J$4="No",C95,0) -> 0 | D104: =IF(Inputs!$J$4="No",D95,0) -> 0 | E104: =IF(Inputs!$J$4="No",E95,0) -> 0
B105: P&L — Total Revenue (₹) | C105: =C103+C104 -> 119411930 | D105: =D103+D104 -> 133098190 | E105: =E103+E104 -> 143879330
B106: P&L — Total Operating Expenses (₹) | C106: =C100 -> 1.2067523e+08 | D106: =D100 -> 1.1716042e+08 | E106: =E100 -> 1.1481721e+08
B107: P&L — Net Surplus / (Deficit) (₹) | C107: =C105-C106 -> -1263300.9 | D107: =D105-D106 -> 15937772 | E107: =E105-E106 -> 29062120
B109: Fee-Increase Breakeven Dropout Threshold (count, fixed) | C109: =Calculations!$G$81 -> 54 | D109: =Calculations!$G$81 -> 54 | E109: =Calculations!$G$81 -> 54
B110: Headroom vs Breakeven Dropouts (count, after scholarship) | C110: =C109-C89 -> 26 | D110: =D109-D89 -> 54 | E110: =E109-E89 -> 54
B111: Revenue from Scholarship-Retained Students (₹) | C111: =SUMPRODUCT(Calculations!K6:K20*Inputs!$D$8:$D$22*(1+Inputs!$F$53)) -> 4792330 | D111: =SUMPRODUCT(Calculations!K26:K40*Inputs!$D$8:$D$22*(1+Inputs!$F$53)) -> 7868190 | E111: =SUMPRODUCT(Calculations!K46:K60*Inputs!$D$8:$D$22*(1+Inputs!$F$53)) -> 4792330
B112: Revenue Impact of Fee Increase vs No-Increase (₹, existing students only, net of scholarship) | C112: =SUMPRODUCT((Calculations!C6:C20-Calculations!J6:J20)*Inputs!$D$8:$D$22*(1+Inputs!$E$8:$E$22))+SUMPRODUCT(Calculations!K6:K20*Inputs!$D$8:$D$22*(1+Inputs!$F$53))-Calculations!$H$81 -> 9086530 | D112: =SUMPRODUCT((Calculations!C26:C40-Calculations!J26:J40)*Inputs!$D$8:$D$22*(1+Inputs!$E$8:$E$22))+SUMPRODUCT(Calculations!K26:K40*Inputs!$D$8:$D$22*(1+Inputs!$F$53))-Calculations!$H$81 -> 17251590 | E112: =SUMPRODUCT((Calculations!C46:C60-Calculations!J46:J60)*Inputs!$D$8:$D$22*(1+Inputs!$E$8:$E$22))+SUMPRODUCT(Calculations!K46:K60*Inputs!$D$8:$D$22*(1+Inputs!$F$53))-Calculations!$H$81 -> 17442130
B114: Returnable Fund — Opening Balance (₹) | C114: =Inputs!$F$47 -> 0 | D114: =Inputs!$F$47 -> 0 | E114: =Inputs!$F$47 -> 0
B115: Returnable Fund — Additions (₹) | C115: =C94+IF(Inputs!$J$4="Yes",C95,0) -> 8380000 | D115: =D94+IF(Inputs!$J$4="Yes",D95,0) -> 13900000 | E115: =E94+IF(Inputs!$J$4="Yes",E95,0) -> 20800000
B116: Returnable Fund — Refunds Paid (₹) | C116: =Inputs!$F$48 -> 0 | D116: =Inputs!$F$48 -> 0 | E116: =Inputs!$F$48 -> 0
B117: Returnable Fund — Closing Balance (₹) | C117: =C114+C115-C116 -> 8380000 | D117: =D114+D115-D116 -> 13900000 | E117: =E114+E115-E116 -> 20800000
